{"_id": "6418b93909150c1101014d37", "id": "facebook/fasttext-ml-vectors", "private": false, "pipeline_tag": "feature-extraction", "library_name": "fasttext", "tags": ["fasttext", "feature-extraction", "ml", "arxiv:1607.04606", "arxiv:1802.06893", "arxiv:1607.01759", "arxiv:1612.03651", "license:cc-by-sa-3.0", "region:us"], "downloads": 152, "likes": 0, "modelId": "facebook/fasttext-ml-vectors", "author": "facebook", "sha": "3fae9daa2a574c5739aa47730cc9cd4d97b383c4", "lastModified": "2023-06-03T22:13:43.000Z", "gated": false, "disabled": false, "widgetData": [{"text": "apple", "example_title": "apple"}], "model-index": null, "cardData": {"license": "cc-by-sa-3.0", "tags": ["feature-extraction"], "library_name": "fasttext", "language": "ml", "widget": [{"text": "apple", "example_title": "apple"}]}, "siblings": [{"rfilename": ".gitattributes"}, {"rfilename": "README.md"}, {"rfilename": "model.bin"}], "spaces": [], "createdAt": "2023-03-20T19:51:21.000Z", "usedStorage": 7287541414, "downloadsAllTime": 349, "inferenceProviderMapping": {}, "configJson": null, "onnxFiles": {}, "safetensorsSizeMb": 0.0, "approxSizeMb": 0.0, "fetchedAt": "2026-06-08T16:42:43.000Z"}