{"_id": "6812874f1e462233872c1a5a", "id": "HyperBlaze/BGE-m3-ko", "private": false, "pipeline_tag": "feature-extraction", "library_name": "transformers.js", "tags": ["transformers.js", "onnx", "xlm-roberta", "feature-extraction", "ko", "en", "base_model:BAAI/bge-m3", "base_model:quantized:BAAI/bge-m3", "license:apache-2.0", "region:us"], "downloads": 69, "likes": 1, "modelId": "HyperBlaze/BGE-m3-ko", "author": "HyperBlaze", "sha": "0bcfa27159d1779abfeeb240fc2d5331cbc205e6", "lastModified": "2025-04-30T20:47:51.000Z", "gated": false, "disabled": false, "mask_token": "<mask>", "model-index": null, "config": {"architectures": ["XLMRobertaModel"], "model_type": "xlm-roberta", "tokenizer_config": {"bos_token": "<s>", "cls_token": "<s>", "eos_token": "</s>", "mask_token": "<mask>", "pad_token": "<pad>", "sep_token": "</s>", "unk_token": "<unk>"}}, "cardData": {"license": "apache-2.0", "language": ["ko", "en"], "base_model": ["BAAI/bge-m3", "dragonkue/BGE-m3-ko"], "pipeline_tag": "feature-extraction", "library_name": "transformers.js"}, "transformersInfo": {"auto_model": "AutoModelForMultimodalLM", "pipeline_tag": "feature-extraction", "processor": "AutoTokenizer"}, "siblings": [{"rfilename": ".gitattributes"}, {"rfilename": "README.md"}, {"rfilename": "config.json"}, {"rfilename": "onnx/model.onnx"}, {"rfilename": "onnx/model.onnx_data"}, {"rfilename": "onnx/model_bnb4.onnx"}, {"rfilename": "onnx/model_fp16.onnx"}, {"rfilename": "onnx/model_int8.onnx"}, {"rfilename": "onnx/model_q4.onnx"}, {"rfilename": "onnx/model_q4f16.onnx"}, {"rfilename": "onnx/model_quantized.onnx"}, {"rfilename": "onnx/model_uint8.onnx"}, {"rfilename": "quantize_config.json"}, {"rfilename": "special_tokens_map.json"}, {"rfilename": "tokenizer.json"}, {"rfilename": "tokenizer_config.json"}], "spaces": [], "createdAt": "2025-04-30T20:25:51.000Z", "usedStorage": 7736129504, "downloadsAllTime": 1263, "inferenceProviderMapping": {}, "configJson": {"_attn_implementation_autoset": true, "_name_or_path": "dragonkue/BGE-m3-ko", "architectures": ["XLMRobertaModel"], "attention_probs_dropout_prob": 0.1, "bos_token_id": 0, "classifier_dropout": null, "eos_token_id": 2, "export_model_type": "transformer", "hidden_act": "gelu", "hidden_dropout_prob": 0.1, "hidden_size": 1024, "initializer_range": 0.02, "intermediate_size": 4096, "layer_norm_eps": 1e-05, "max_position_embeddings": 8194, "model_type": "xlm-roberta", "num_attention_heads": 16, "num_hidden_layers": 24, "output_past": true, "pad_token_id": 1, "position_embedding_type": "absolute", "torch_dtype": "float32", "transformers_version": "4.49.0", "type_vocab_size": 1, "use_cache": true, "vocab_size": 250002}, "onnxFiles": {"onnx/model.onnx": 0.7, "onnx/model_bnb4.onnx": 1229.5, "onnx/model_fp16.onnx": 1134.1, "onnx/model_int8.onnx": 569.7, "onnx/model_q4.onnx": 1248.4, "onnx/model_q4f16.onnx": 700.1, "onnx/model_quantized.onnx": 569.7, "onnx/model_uint8.onnx": 569.7}, "safetensorsSizeMb": 0.0, "approxSizeMb": 0.0, "fetchedAt": "2026-06-09T22:07:05.000Z"}