{"_id": "698467bab7772387576068d8", "id": "Maksim-KOS/embeddinggemma-300m-saturn-planet", "private": false, "pipeline_tag": "sentence-similarity", "library_name": "sentence-transformers", "tags": ["sentence-transformers", "safetensors", "gemma3_text", "sentence-similarity", "feature-extraction", "dense", "generated_from_trainer", "dataset_size:123502", "loss:MultipleNegativesRankingLoss", "arxiv:1908.10084", "arxiv:1705.00652", "base_model:google/embeddinggemma-300m", "base_model:finetune:google/embeddinggemma-300m", "model-index", "text-embeddings-inference", "endpoints_compatible", "region:us"], "downloads": 20, "likes": 0, "modelId": "Maksim-KOS/embeddinggemma-300m-saturn-planet", "author": "Maksim-KOS", "sha": "def8c0315ef7bee6c742fa8b7bd3cd01a2e1f05e", "lastModified": "2026-02-05T09:51:26.000Z", "gated": false, "disabled": false, "widgetData": [{"source_sentence": "стержни клеевые 11 x 200 mm прозрачные", "sentences": ["шпаклевка danogips superfinish готовая 18 кг", "стержни для клеевого пистолета biber 60131 прозр. 11 x 200 mm 6 шт.", "наличник деревянный прямой сращенный сорт экстра 11 x 90 x 2200 mm"]}, {"source_sentence": "стамеска 18 mm biber мастер", "sentences": ["стамеска biber 85057 мастер 18 mm", "стамеска biber 85053 мастер 10 mm", "наконечник ншви 2 6 0 14 для провода 6 mm2 100 шт."]}, {"source_sentence": "саморез 3.8 x 41 mm шсгд", "sentences": ["коробка упаковочная сатурн 550 x 380 x 300 mm картон", "саморез swfs шсгд 3.8 x 51 200 шт", "саморез swfs шсгд zy 3.8 x 41 25 шт пакетик"]}, {"source_sentence": "гибкое стекло 140 x 80 см", "sentences": ["гибкое стекло dekorelle 140 x 80 см", "стекломагнезитовый лист стандарт 2500 x 1220 x 8 mm", "труба valfex полипропилен арmир. стекл. d 40 x 5.5 mm pn 20 4 m"]}, {"source_sentence": "трап горизонтальный 100 x 100 mm d50 mm с гидрозатвором", "sentences": ["лоток водоотводный standartpark basic dn100 1000 x 156 x 120 mm пластик 8020 m", "трап ани пласт горизонтальный d 50 mm 100 x 100 mm не регулируемый гидрозатвор", "саморез шуж swfs pn 4 x 12 1000 шт"]}], "model-index": [{"name": "SentenceTransformer based on google/embeddinggemma-300m", "results": [{"task": {"type": "triplet", "name": "Triplet"}, "dataset": {"name": "hard neg eval", "type": "hard-neg-eval"}, "metrics": [{"type": "cosine_accuracy", "value": 0.9975224137306213, "name": "Cosine Accuracy", "verified": false}]}]}], "config": {"architectures": ["Gemma3TextModel"], "model_type": "gemma3_text", "tokenizer_config": {"bos_token": "<bos>", "eos_token": "<eos>", "pad_token": "<pad>", "unk_token": "<unk>", "use_default_system_prompt": false}}, "cardData": {"tags": ["sentence-transformers", "sentence-similarity", "feature-extraction", "dense", "generated_from_trainer", "dataset_size:123502", "loss:MultipleNegativesRankingLoss"], "base_model": "google/embeddinggemma-300m", "widget": [{"source_sentence": "стержни клеевые 11 x 200 mm прозрачные", "sentences": ["шпаклевка danogips superfinish готовая 18 кг", "стержни для клеевого пистолета biber 60131 прозр. 11 x 200 mm 6 шт.", "наличник деревянный прямой сращенный сорт экстра 11 x 90 x 2200 mm"]}, {"source_sentence": "стамеска 18 mm biber мастер", "sentences": ["стамеска biber 85057 мастер 18 mm", "стамеска biber 85053 мастер 10 mm", "наконечник ншви 2 6 0 14 для провода 6 mm2 100 шт."]}, {"source_sentence": "саморез 3.8 x 41 mm шсгд", "sentences": ["коробка упаковочная сатурн 550 x 380 x 300 mm картон", "саморез swfs шсгд 3.8 x 51 200 шт", "саморез swfs шсгд zy 3.8 x 41 25 шт пакетик"]}, {"source_sentence": "гибкое стекло 140 x 80 см", "sentences": ["гибкое стекло dekorelle 140 x 80 см", "стекломагнезитовый лист стандарт 2500 x 1220 x 8 mm", "труба valfex полипропилен арmир. стекл. d 40 x 5.5 mm pn 20 4 m"]}, {"source_sentence": "трап горизонтальный 100 x 100 mm d50 mm с гидрозатвором", "sentences": ["лоток водоотводный standartpark basic dn100 1000 x 156 x 120 mm пластик 8020 m", "трап ани пласт горизонтальный d 50 mm 100 x 100 mm не регулируемый гидрозатвор", "саморез шуж swfs pn 4 x 12 1000 шт"]}], "pipeline_tag": "sentence-similarity", "library_name": "sentence-transformers", "metrics": ["cosine_accuracy"], "model-index": [{"name": "SentenceTransformer based on google/embeddinggemma-300m", "results": [{"task": {"type": "triplet", "name": "Triplet"}, "dataset": {"name": "hard neg eval", "type": "hard-neg-eval"}, "metrics": [{"type": "cosine_accuracy", "value": 0.9975224137306213, "name": "Cosine Accuracy", "verified": false}]}]}]}, "siblings": [{"rfilename": ".gitattributes"}, {"rfilename": "1_Pooling/config.json"}, {"rfilename": "2_Dense/config.json"}, {"rfilename": "2_Dense/model.safetensors"}, {"rfilename": "3_Dense/config.json"}, {"rfilename": "3_Dense/model.safetensors"}, {"rfilename": "README.md"}, {"rfilename": "config.json"}, {"rfilename": "config_sentence_transformers.json"}, {"rfilename": "model.safetensors"}, {"rfilename": "modules.json"}, {"rfilename": "sentence_bert_config.json"}, {"rfilename": "special_tokens_map.json"}, {"rfilename": "tokenizer.json"}, {"rfilename": "tokenizer_config.json"}], "spaces": [], "createdAt": "2026-02-05T09:49:46.000Z", "safetensors": {"parameters": {"F32": 302863104}, "total": 302863104}, "usedStorage": 1263745878, "downloadsAllTime": 738, "inferenceProviderMapping": {}, "configJson": {"_sliding_window_pattern": 6, "architectures": ["Gemma3TextModel"], "attention_bias": false, "attention_dropout": 0.0, "attn_logit_softcapping": null, "bos_token_id": 2, "dtype": "float32", "eos_token_id": 1, "final_logit_softcapping": null, "head_dim": 256, "hidden_activation": "gelu_pytorch_tanh", "hidden_size": 768, "initializer_range": 0.02, "intermediate_size": 1152, "layer_types": ["sliding_attention", "sliding_attention", "sliding_attention", "sliding_attention", "sliding_attention", "full_attention", "sliding_attention", "sliding_attention", "sliding_attention", "sliding_attention", "sliding_attention", "full_attention", "sliding_attention", "sliding_attention", "sliding_attention", "sliding_attention", "sliding_attention", "full_attention", "sliding_attention", "sliding_attention", "sliding_attention", "sliding_attention", "sliding_attention", "full_attention"], "max_position_embeddings": 2048, "model_type": "gemma3_text", "num_attention_heads": 3, "num_hidden_layers": 24, "num_key_value_heads": 1, "pad_token_id": 0, "query_pre_attn_scalar": 256, "rms_norm_eps": 1e-06, "rope_local_base_freq": 10000.0, "rope_scaling": null, "rope_theta": 1000000.0, "sliding_window": 129, "transformers_version": "4.57.6", "use_bidirectional_attention": true, "use_cache": true, "vocab_size": 262144}, "onnxFiles": {}, "safetensorsSizeMb": 1230.4, "approxSizeMb": 1211.5, "fetchedAt": "2026-06-08T16:42:43.000Z"}