{"_id": "6926c78e20b43a4198fb8575", "id": "LamaDiab/v3MiniLM-V18Data-256ConstantBATCH-SemanticEngine", "private": false, "pipeline_tag": "sentence-similarity", "library_name": "sentence-transformers", "tags": ["sentence-transformers", "safetensors", "bert", "sentence-similarity", "feature-extraction", "dense", "generated_from_trainer", "dataset_size:705905", "loss:MultipleNegativesSymmetricRankingLoss", "arxiv:1908.10084", "base_model:sentence-transformers/all-MiniLM-L6-v2", "base_model:finetune:sentence-transformers/all-MiniLM-L6-v2", "model-index", "text-embeddings-inference", "endpoints_compatible", "region:us"], "downloads": 2, "likes": 0, "modelId": "LamaDiab/v3MiniLM-V18Data-256ConstantBATCH-SemanticEngine", "author": "LamaDiab", "sha": "c618bb604d45df6925430dcee7e36b3506e6cd3a", "lastModified": "2025-11-26T12:52:13.000Z", "gated": false, "disabled": false, "mask_token": "[MASK]", "widgetData": [{"source_sentence": "gerber baby food fruits apples bananas & cereal", "sentences": ["world of sweets puzzle", "baby food", "baby food"]}, {"source_sentence": "granville original one bite original rice crispy squares", "sentences": [" one bite rice crispy ", "sweet", "bounty wafer rolls"]}, {"source_sentence": "rosa / porcelain us andalusia mug", "sentences": ["mug", " rosa mug", "melamine small plate - teal"]}, {"source_sentence": "cetaphil sunscreen spf 50+ cream 89 ml", "sentences": ["sunscreen", " cetaphil sunscreen cream", "garnier intensity (6.60) intense ruby"]}, {"source_sentence": "italian dolce provolone", "sentences": ["trident - gum strawberry flavor - 5 per pack", "experience the authentic taste of italy with our italian dolce provolone. indulge in its creamy texture, delicate flavors, and versatility in both simple and sophisticated culinary creations.", "dairy"]}], "model-index": [{"name": "SentenceTransformer based on sentence-transformers/all-MiniLM-L6-v2", "results": [{"task": {"type": "triplet", "name": "Triplet"}, "dataset": {"name": "Unknown", "type": "unknown"}, "metrics": [{"type": "cosine_accuracy", "value": 0.9695025682449341, "name": "Cosine Accuracy", "verified": false}]}]}], "config": {"architectures": ["BertModel"], "model_type": "bert", "tokenizer_config": {"cls_token": "[CLS]", "mask_token": "[MASK]", "pad_token": "[PAD]", "sep_token": "[SEP]", "unk_token": "[UNK]"}}, "cardData": {"tags": ["sentence-transformers", "sentence-similarity", "feature-extraction", "dense", "generated_from_trainer", "dataset_size:705905", "loss:MultipleNegativesSymmetricRankingLoss"], "base_model": "sentence-transformers/all-MiniLM-L6-v2", "widget": [{"source_sentence": "gerber baby food fruits apples bananas & cereal", "sentences": ["world of sweets puzzle", "baby food", "baby food"]}, {"source_sentence": "granville original one bite original rice crispy squares", "sentences": [" one bite rice crispy ", "sweet", "bounty wafer rolls"]}, {"source_sentence": "rosa / porcelain us andalusia mug", "sentences": ["mug", " rosa mug", "melamine small plate - teal"]}, {"source_sentence": "cetaphil sunscreen spf 50+ cream 89 ml", "sentences": ["sunscreen", " cetaphil sunscreen cream", "garnier intensity (6.60) intense ruby"]}, {"source_sentence": "italian dolce provolone", "sentences": ["trident - gum strawberry flavor - 5 per pack", "experience the authentic taste of italy with our italian dolce provolone. indulge in its creamy texture, delicate flavors, and versatility in both simple and sophisticated culinary creations.", "dairy"]}], "pipeline_tag": "sentence-similarity", "library_name": "sentence-transformers", "metrics": ["cosine_accuracy"], "model-index": [{"name": "SentenceTransformer based on sentence-transformers/all-MiniLM-L6-v2", "results": [{"task": {"type": "triplet", "name": "Triplet"}, "dataset": {"name": "Unknown", "type": "unknown"}, "metrics": [{"type": "cosine_accuracy", "value": 0.9695025682449341, "name": "Cosine Accuracy", "verified": false}]}]}]}, "siblings": [{"rfilename": ".gitattributes"}, {"rfilename": "1_Pooling/config.json"}, {"rfilename": "README.md"}, {"rfilename": "checkpoint-11038/1_Pooling/config.json"}, {"rfilename": "checkpoint-11038/README.md"}, {"rfilename": "checkpoint-11038/config.json"}, {"rfilename": "checkpoint-11038/config_sentence_transformers.json"}, {"rfilename": "checkpoint-11038/model.safetensors"}, {"rfilename": "checkpoint-11038/modules.json"}, {"rfilename": "checkpoint-11038/optimizer.pt"}, {"rfilename": "checkpoint-11038/rng_state.pth"}, {"rfilename": "checkpoint-11038/scaler.pt"}, {"rfilename": "checkpoint-11038/scheduler.pt"}, {"rfilename": "checkpoint-11038/sentence_bert_config.json"}, {"rfilename": "checkpoint-11038/special_tokens_map.json"}, {"rfilename": "checkpoint-11038/tokenizer.json"}, {"rfilename": "checkpoint-11038/tokenizer_config.json"}, {"rfilename": "checkpoint-11038/trainer_state.json"}, {"rfilename": "checkpoint-11038/training_args.bin"}, {"rfilename": "checkpoint-11038/vocab.txt"}, {"rfilename": "checkpoint-13798/1_Pooling/config.json"}, {"rfilename": "checkpoint-13798/README.md"}, {"rfilename": "checkpoint-13798/config.json"}, {"rfilename": "checkpoint-13798/config_sentence_transformers.json"}, {"rfilename": "checkpoint-13798/model.safetensors"}, {"rfilename": "checkpoint-13798/modules.json"}, {"rfilename": "checkpoint-13798/optimizer.pt"}, {"rfilename": "checkpoint-13798/rng_state.pth"}, {"rfilename": "checkpoint-13798/scaler.pt"}, {"rfilename": "checkpoint-13798/scheduler.pt"}, {"rfilename": "checkpoint-13798/sentence_bert_config.json"}, {"rfilename": "checkpoint-13798/special_tokens_map.json"}, {"rfilename": "checkpoint-13798/tokenizer.json"}, {"rfilename": "checkpoint-13798/tokenizer_config.json"}, {"rfilename": "checkpoint-13798/trainer_state.json"}, {"rfilename": "checkpoint-13798/training_args.bin"}, {"rfilename": "checkpoint-13798/vocab.txt"}, {"rfilename": "checkpoint-16548/1_Pooling/config.json"}, {"rfilename": "checkpoint-16548/README.md"}, {"rfilename": "checkpoint-16548/config.json"}, {"rfilename": "checkpoint-16548/config_sentence_transformers.json"}, {"rfilename": "checkpoint-16548/model.safetensors"}, {"rfilename": "checkpoint-16548/modules.json"}, {"rfilename": "checkpoint-16548/optimizer.pt"}, {"rfilename": "checkpoint-16548/rng_state.pth"}, {"rfilename": "checkpoint-16548/scaler.pt"}, {"rfilename": "checkpoint-16548/scheduler.pt"}, {"rfilename": "checkpoint-16548/sentence_bert_config.json"}, {"rfilename": "checkpoint-16548/special_tokens_map.json"}, {"rfilename": "checkpoint-16548/tokenizer.json"}, {"rfilename": "checkpoint-16548/tokenizer_config.json"}, {"rfilename": "checkpoint-16548/trainer_state.json"}, {"rfilename": "checkpoint-16548/training_args.bin"}, {"rfilename": "checkpoint-16548/vocab.txt"}, {"rfilename": "checkpoint-2758/1_Pooling/config.json"}, {"rfilename": "checkpoint-2758/README.md"}, {"rfilename": "checkpoint-2758/config.json"}, {"rfilename": "checkpoint-2758/config_sentence_transformers.json"}, {"rfilename": "checkpoint-2758/model.safetensors"}, {"rfilename": "checkpoint-2758/modules.json"}, {"rfilename": "checkpoint-2758/optimizer.pt"}, {"rfilename": "checkpoint-2758/rng_state.pth"}, {"rfilename": "checkpoint-2758/scaler.pt"}, {"rfilename": "checkpoint-2758/scheduler.pt"}, {"rfilename": "checkpoint-2758/sentence_bert_config.json"}, {"rfilename": "checkpoint-2758/special_tokens_map.json"}, {"rfilename": "checkpoint-2758/tokenizer.json"}, {"rfilename": "checkpoint-2758/tokenizer_config.json"}, {"rfilename": "checkpoint-2758/trainer_state.json"}, {"rfilename": "checkpoint-2758/training_args.bin"}, {"rfilename": "checkpoint-2758/vocab.txt"}, {"rfilename": "checkpoint-5518/1_Pooling/config.json"}, {"rfilename": "checkpoint-5518/README.md"}, {"rfilename": "checkpoint-5518/config.json"}, {"rfilename": "checkpoint-5518/config_sentence_transformers.json"}, {"rfilename": "checkpoint-5518/model.safetensors"}, {"rfilename": "checkpoint-5518/modules.json"}, {"rfilename": "checkpoint-5518/optimizer.pt"}, {"rfilename": "checkpoint-5518/rng_state.pth"}, {"rfilename": "checkpoint-5518/scaler.pt"}, {"rfilename": "checkpoint-5518/scheduler.pt"}, {"rfilename": "checkpoint-5518/sentence_bert_config.json"}, {"rfilename": "checkpoint-5518/special_tokens_map.json"}, {"rfilename": "checkpoint-5518/tokenizer.json"}, {"rfilename": "checkpoint-5518/tokenizer_config.json"}, {"rfilename": "checkpoint-5518/trainer_state.json"}, {"rfilename": "checkpoint-5518/training_args.bin"}, {"rfilename": "checkpoint-5518/vocab.txt"}, {"rfilename": "checkpoint-8278/1_Pooling/config.json"}, {"rfilename": "checkpoint-8278/README.md"}, {"rfilename": "checkpoint-8278/config.json"}, {"rfilename": "checkpoint-8278/config_sentence_transformers.json"}, {"rfilename": "checkpoint-8278/model.safetensors"}, {"rfilename": "checkpoint-8278/modules.json"}, {"rfilename": "checkpoint-8278/optimizer.pt"}, {"rfilename": "checkpoint-8278/rng_state.pth"}, {"rfilename": "checkpoint-8278/scaler.pt"}, {"rfilename": "checkpoint-8278/scheduler.pt"}, {"rfilename": "checkpoint-8278/sentence_bert_config.json"}, {"rfilename": "checkpoint-8278/special_tokens_map.json"}, {"rfilename": "checkpoint-8278/tokenizer.json"}, {"rfilename": "checkpoint-8278/tokenizer_config.json"}, {"rfilename": "checkpoint-8278/trainer_state.json"}, {"rfilename": "checkpoint-8278/training_args.bin"}, {"rfilename": "checkpoint-8278/vocab.txt"}, {"rfilename": "config.json"}, {"rfilename": "config_sentence_transformers.json"}, {"rfilename": "eval/triplet_evaluation_results.csv"}, {"rfilename": "model.safetensors"}, {"rfilename": "modules.json"}, {"rfilename": "sentence_bert_config.json"}, {"rfilename": "special_tokens_map.json"}, {"rfilename": "tokenizer.json"}, {"rfilename": "tokenizer_config.json"}, {"rfilename": "training_args.bin"}, {"rfilename": "vocab.txt"}], "spaces": [], "createdAt": "2025-11-26T09:25:34.000Z", "safetensors": {"parameters": {"F32": 22713216}, "total": 22713216}, "usedStorage": 1628955104, "downloadsAllTime": 6, "inferenceProviderMapping": {}, "configJson": {"architectures": ["BertModel"], "attention_probs_dropout_prob": 0.1, "classifier_dropout": null, "gradient_checkpointing": false, "hidden_act": "gelu", "hidden_dropout_prob": 0.1, "hidden_size": 384, "initializer_range": 0.02, "intermediate_size": 1536, "layer_norm_eps": 1e-12, "max_position_embeddings": 512, "model_type": "bert", "num_attention_heads": 12, "num_hidden_layers": 6, "pad_token_id": 0, "position_embedding_type": "absolute", "torch_dtype": "float32", "transformers_version": "4.53.3", "type_vocab_size": 2, "use_cache": true, "vocab_size": 30522}, "onnxFiles": {}, "safetensorsSizeMb": 636.0, "approxSizeMb": 90.9, "fetchedAt": "2026-06-09T06:55:53.000Z"}