{"_id": "669fbff8655e8727db59518a", "id": "Nada-10/f-jp-multilingual-e5-small", "private": false, "pipeline_tag": "sentence-similarity", "library_name": "sentence-transformers", "tags": ["sentence-transformers", "safetensors", "bert", "sentence-similarity", "feature-extraction", "generated_from_trainer", "dataset_size:1446", "loss:MultipleNegativesRankingLoss", "arxiv:1908.10084", "arxiv:1705.00652", "base_model:intfloat/multilingual-e5-small", "base_model:finetune:intfloat/multilingual-e5-small", "text-embeddings-inference", "endpoints_compatible", "region:us"], "downloads": 6, "likes": 0, "modelId": "Nada-10/f-jp-multilingual-e5-small", "author": "Nada-10", "sha": "b1642208ddc8b9e2ed8360f97d564e4de9d73f57", "lastModified": "2024-07-23T14:44:27.000Z", "gated": false, "disabled": false, "mask_token": "[MASK]", "widgetData": [{"source_sentence": "圧縮機の回転部分の総称であって、動翼を介して気体に仕事を付加する機能をもつ。動翼を植えてないも のを圧縮機ロータという場合がある。", "sentences": ["圧縮機ロータ〔コンプレッサロータ〕はどのように定義されていますか？", "溶存水素の定義を教えてください。", "中圧圧縮機〔中圧コンプレッサ〕の定義は何ですか？"]}, {"source_sentence": "気体を圧縮、加熱し連続的に膨張させて、その保有する熱エネルギーを機械的エネルギーとして取り出 す熱機関。原則として圧縮機、加熱器、タービン、制御装置のほか必要に応じて熱交換器その他の補機 からなっている。", "sentences": ["What is the definition of gas turbine?", "What is the definition of low fuel pressure tripping device?", "微分動作〔Ｄ動作〕の機能は何ですか？"]}, {"source_sentence": "光の透過または散乱を利用して水のにごりの度合を示す計器。", "sentences": ["第３リン酸ソーダの機能は何ですか？", "濁度計をどのように定義しますか？", "How is 〔ＤＥＢ〕　direct　energy　balance　coordinated　control〔ＡＰＣ〕　automatic　power　control、automatic　plant　control defined?"]}, {"source_sentence": "ボイラ用水として使用している水の不純物の除去および軟化、ｐＨの調整等の処理をいう。", "sentences": ["給水処理の機能は何ですか？", "除湿器の機能は何ですか？", "薬液貯蔵タンクの意味を説明してください。"]}, {"source_sentence": "再生時アニオン樹脂とカチオン樹脂は別々に再生される。再生後両樹脂の混合に用いる送風機をいう。", "sentences": ["中和装置の定義は何ですか？", "混床塔ブロワをどのように定義しますか？", "How is  raw water defined?"]}], "model-index": null, "config": {"architectures": ["BertModel"], "model_type": "bert", "tokenizer_config": {"bos_token": "<s>", "cls_token": "<s>", "eos_token": "</s>", "mask_token": "<mask>", "pad_token": "<pad>", "sep_token": "</s>", "unk_token": "<unk>"}}, "cardData": {"base_model": "intfloat/multilingual-e5-small", "datasets": [], "language": [], "library_name": "sentence-transformers", "pipeline_tag": "sentence-similarity", "tags": ["sentence-transformers", "sentence-similarity", "feature-extraction", "generated_from_trainer", "dataset_size:1446", "loss:MultipleNegativesRankingLoss"], "widget": [{"source_sentence": "圧縮機の回転部分の総称であって、動翼を介して気体に仕事を付加する機能をもつ。動翼を植えてないも のを圧縮機ロータという場合がある。", "sentences": ["圧縮機ロータ〔コンプレッサロータ〕はどのように定義されていますか？", "溶存水素の定義を教えてください。", "中圧圧縮機〔中圧コンプレッサ〕の定義は何ですか？"]}, {"source_sentence": "気体を圧縮、加熱し連続的に膨張させて、その保有する熱エネルギーを機械的エネルギーとして取り出 す熱機関。原則として圧縮機、加熱器、タービン、制御装置のほか必要に応じて熱交換器その他の補機 からなっている。", "sentences": ["What is the definition of gas turbine?", "What is the definition of low fuel pressure tripping device?", "微分動作〔Ｄ動作〕の機能は何ですか？"]}, {"source_sentence": "光の透過または散乱を利用して水のにごりの度合を示す計器。", "sentences": ["第３リン酸ソーダの機能は何ですか？", "濁度計をどのように定義しますか？", "How is 〔ＤＥＢ〕　direct　energy　balance　coordinated　control〔ＡＰＣ〕　automatic　power　control、automatic　plant　control defined?"]}, {"source_sentence": "ボイラ用水として使用している水の不純物の除去および軟化、ｐＨの調整等の処理をいう。", "sentences": ["給水処理の機能は何ですか？", "除湿器の機能は何ですか？", "薬液貯蔵タンクの意味を説明してください。"]}, {"source_sentence": "再生時アニオン樹脂とカチオン樹脂は別々に再生される。再生後両樹脂の混合に用いる送風機をいう。", "sentences": ["中和装置の定義は何ですか？", "混床塔ブロワをどのように定義しますか？", "How is  raw water defined?"]}]}, "siblings": [{"rfilename": ".gitattributes"}, {"rfilename": "1_Pooling/config.json"}, {"rfilename": "README.md"}, {"rfilename": "config.json"}, {"rfilename": "config_sentence_transformers.json"}, {"rfilename": "model.safetensors"}, {"rfilename": "modules.json"}, {"rfilename": "sentence_bert_config.json"}, {"rfilename": "special_tokens_map.json"}, {"rfilename": "tokenizer.json"}, {"rfilename": "tokenizer_config.json"}], "spaces": [], "createdAt": "2024-07-23T14:36:40.000Z", "safetensors": {"parameters": {"F32": 117653760}, "total": 117653760}, "usedStorage": 487720469, "downloadsAllTime": 16, "inferenceProviderMapping": {}, "configJson": {"_name_or_path": "intfloat/multilingual-e5-small", "architectures": ["BertModel"], "attention_probs_dropout_prob": 0.1, "classifier_dropout": null, "hidden_act": "gelu", "hidden_dropout_prob": 0.1, "hidden_size": 384, "initializer_range": 0.02, "intermediate_size": 1536, "layer_norm_eps": 1e-12, "max_position_embeddings": 512, "model_type": "bert", "num_attention_heads": 12, "num_hidden_layers": 12, "pad_token_id": 0, "position_embedding_type": "absolute", "tokenizer_class": "XLMRobertaTokenizer", "torch_dtype": "float32", "transformers_version": "4.42.4", "type_vocab_size": 2, "use_cache": true, "vocab_size": 250037}, "onnxFiles": {}, "safetensorsSizeMb": 470.6, "approxSizeMb": 470.6, "fetchedAt": "2026-06-09T06:55:53.000Z"}