{"_id": "665cba500f35c005de3a4bc2", "id": "slimaneMakh/triplet_CloseHlabel_farLabel_andnegativ-1M-5eps-XLMR_29may", "private": false, "pipeline_tag": "sentence-similarity", "library_name": "sentence-transformers", "tags": ["sentence-transformers", "safetensors", "xlm-roberta", "sentence-similarity", "feature-extraction", "dataset_size:100K<n<1M", "loss:TripletLoss", "arxiv:1908.10084", "arxiv:1703.07737", "base_model:FacebookAI/xlm-roberta-base", "base_model:finetune:FacebookAI/xlm-roberta-base", "model-index", "text-embeddings-inference", "endpoints_compatible", "region:us"], "downloads": 2, "likes": 1, "modelId": "slimaneMakh/triplet_CloseHlabel_farLabel_andnegativ-1M-5eps-XLMR_29may", "author": "slimaneMakh", "sha": "6977101923f19357e90a952533b84c6fc8bdacba", "lastModified": "2024-06-02T18:31:13.000Z", "gated": false, "disabled": false, "mask_token": "<mask>", "widgetData": [{"source_sentence": "Skip", "sentences": ["Ships", "Kapital akcyjny", "Other finance income"]}, {"source_sentence": "IIII", "sentences": ["iii", "Gauti dividendai", "Loans given"]}, {"source_sentence": "IVE", "sentences": ["HH", "Koszty finansowe", "Current borrowings"]}, {"source_sentence": "K K", "sentences": ["TOTAL ACTIF", "Nuomos mokejimai", "Accruals"]}, {"source_sentence": "Sales", "sentences": ["Revenue", "Operating profit", "Current borrowings"]}], "model-index": [{"name": "SentenceTransformer based on FacebookAI/xlm-roberta-base", "results": [{"task": {"type": "triplet", "name": "Triplet"}, "dataset": {"name": "Unknown", "type": "unknown"}, "metrics": [{"type": "cosine_accuracy", "value": 0.9987885552019722, "name": "Cosine Accuracy", "verified": false}, {"type": "dot_accuracy", "value": 0.001529316610921369, "name": "Dot Accuracy", "verified": false}, {"type": "manhattan_accuracy", "value": 0.9975135360413657, "name": "Manhattan Accuracy", "verified": false}, {"type": "euclidean_accuracy", "value": 0.9990958312877694, "name": "Euclidean Accuracy", "verified": false}, {"type": "max_accuracy", "value": 0.9990958312877694, "name": "Max Accuracy", "verified": false}]}]}], "config": {"architectures": ["XLMRobertaModel"], "model_type": "xlm-roberta", "tokenizer_config": {"bos_token": "<s>", "cls_token": "<s>", "eos_token": "</s>", "mask_token": "<mask>", "pad_token": "<pad>", "sep_token": "</s>", "unk_token": "<unk>"}}, "cardData": {"language": [], "library_name": "sentence-transformers", "tags": ["sentence-transformers", "sentence-similarity", "feature-extraction", "dataset_size:100K<n<1M", "loss:TripletLoss"], "base_model": "FacebookAI/xlm-roberta-base", "metrics": ["cosine_accuracy", "dot_accuracy", "manhattan_accuracy", "euclidean_accuracy", "max_accuracy"], "widget": [{"source_sentence": "Skip", "sentences": ["Ships", "Kapital akcyjny", "Other finance income"]}, {"source_sentence": "IIII", "sentences": ["iii", "Gauti dividendai", "Loans given"]}, {"source_sentence": "IVE", "sentences": ["HH", "Koszty finansowe", "Current borrowings"]}, {"source_sentence": "K K", "sentences": ["TOTAL ACTIF", "Nuomos mokejimai", "Accruals"]}, {"source_sentence": "Sales", "sentences": ["Revenue", "Operating profit", "Current borrowings"]}], "pipeline_tag": "sentence-similarity", "model-index": [{"name": "SentenceTransformer based on FacebookAI/xlm-roberta-base", "results": [{"task": {"type": "triplet", "name": "Triplet"}, "dataset": {"name": "Unknown", "type": "unknown"}, "metrics": [{"type": "cosine_accuracy", "value": 0.9987885552019722, "name": "Cosine Accuracy", "verified": false}, {"type": "dot_accuracy", "value": 0.001529316610921369, "name": "Dot Accuracy", "verified": false}, {"type": "manhattan_accuracy", "value": 0.9975135360413657, "name": "Manhattan Accuracy", "verified": false}, {"type": "euclidean_accuracy", "value": 0.9990958312877694, "name": "Euclidean Accuracy", "verified": false}, {"type": "max_accuracy", "value": 0.9990958312877694, "name": "Max Accuracy", "verified": false}]}]}]}, "siblings": [{"rfilename": ".gitattributes"}, {"rfilename": "1_Pooling/config.json"}, {"rfilename": "README.md"}, {"rfilename": "config.json"}, {"rfilename": "config_sentence_transformers.json"}, {"rfilename": "model.safetensors"}, {"rfilename": "modules.json"}, {"rfilename": "sentence_bert_config.json"}, {"rfilename": "sentencepiece.bpe.model"}, {"rfilename": "special_tokens_map.json"}, {"rfilename": "tokenizer.json"}, {"rfilename": "tokenizer_config.json"}], "spaces": [], "createdAt": "2024-06-02T18:30:40.000Z", "safetensors": {"parameters": {"F32": 278043648}, "total": 278043648}, "usedStorage": 1134349156, "downloadsAllTime": 170, "inferenceProviderMapping": {}, "configJson": {"_name_or_path": "xlm-roberta-base", "architectures": ["XLMRobertaModel"], "attention_probs_dropout_prob": 0.1, "bos_token_id": 0, "classifier_dropout": null, "eos_token_id": 2, "hidden_act": "gelu", "hidden_dropout_prob": 0.1, "hidden_size": 768, "initializer_range": 0.02, "intermediate_size": 3072, "layer_norm_eps": 1e-05, "max_position_embeddings": 514, "model_type": "xlm-roberta", "num_attention_heads": 12, "num_hidden_layers": 12, "output_past": true, "pad_token_id": 1, "position_embedding_type": "absolute", "torch_dtype": "float32", "transformers_version": "4.39.3", "type_vocab_size": 1, "use_cache": true, "vocab_size": 250002}, "onnxFiles": {}, "safetensorsSizeMb": 1112.2, "approxSizeMb": 1112.2, "fetchedAt": "2026-06-09T06:55:53.000Z"}