{"_id": "69ec4b780c632e51575e86d9", "id": "RafaelUI/literary-minilm", "private": false, "pipeline_tag": "sentence-similarity", "library_name": "sentence-transformers", "tags": ["sentence-transformers", "coreml", "safetensors", "sentence-similarity", "feature-extraction", "literary", "semantic-search", "multilingual", "en", "ru", "fr", "de", "es", "it", "pt", "dataset:rafaelui/literary-text-pairs", "base_model:sentence-transformers/paraphrase-multilingual-MiniLM-L12-v2", "base_model:quantized:sentence-transformers/paraphrase-multilingual-MiniLM-L12-v2", "license:apache-2.0", "endpoints_compatible", "region:us"], "downloads": 3, "likes": 2, "modelId": "RafaelUI/literary-minilm", "author": "RafaelUI", "sha": "92a6516f32321dc4048b49c9e6eb2b9aaa7e8e8f", "lastModified": "2026-04-25T05:23:40.000Z", "gated": false, "disabled": false, "widgetData": [{"source_sentence": "That is a happy person", "sentences": ["That is a happy dog", "That is a very happy person", "Today is a sunny day"]}], "model-index": null, "config": {}, "cardData": {"language": ["en", "ru", "fr", "de", "es", "it", "pt"], "license": "apache-2.0", "tags": ["sentence-transformers", "sentence-similarity", "feature-extraction", "literary", "semantic-search", "multilingual"], "base_model": "sentence-transformers/paraphrase-multilingual-MiniLM-L12-v2", "datasets": ["rafaelui/literary-text-pairs"], "pipeline_tag": "sentence-similarity"}, "siblings": [{"rfilename": ".DS_Store"}, {"rfilename": ".gitattributes"}, {"rfilename": "1_Pooling/config.json"}, {"rfilename": "1_Pooling/config_sentence_transformers.json"}, {"rfilename": "1_Pooling/modules.json"}, {"rfilename": "1_Pooling/sentence_bert_config.json"}, {"rfilename": "1_Pooling/tokenizer_config.json"}, {"rfilename": "README.md"}, {"rfilename": "coreml/LiteraryMiniLM.mlpackage/Data/com.apple.CoreML/model.mlmodel"}, {"rfilename": "coreml/LiteraryMiniLM.mlpackage/Data/com.apple.CoreML/weights/weight.bin"}, {"rfilename": "coreml/LiteraryMiniLM.mlpackage/Manifest.json"}, {"rfilename": "model.safetensors"}, {"rfilename": "tokenizer.json"}], "spaces": [], "createdAt": "2026-04-25T05:04:56.000Z", "safetensors": {"parameters": {"F32": 117653760}, "total": 117653760}, "usedStorage": 722684398, "downloadsAllTime": 11, "inferenceProviderMapping": {}, "configJson": null, "onnxFiles": {}, "safetensorsSizeMb": 470.6, "approxSizeMb": 470.6, "fetchedAt": "2026-06-09T06:55:53.000Z"}