{"_id": "690946a7d0070d16fb3d36f7", "id": "SharpAI/dinov3-vits16-pretrain-lvd1689m-coreml-FP32-336x336", "private": false, "pipeline_tag": "feature-extraction", "library_name": "coreml", "tags": ["coreml", "vision", "feature-extraction", "dinov3", "apple-silicon", "fp32", "arxiv:2508.10104", "region:us"], "downloads": 0, "likes": 0, "modelId": "SharpAI/dinov3-vits16-pretrain-lvd1689m-coreml-FP32-336x336", "author": "SharpAI", "sha": "60f478f86837662a8eadb26b057a72913c6114c4", "lastModified": "2025-11-04T00:19:53.000Z", "gated": false, "disabled": false, "model-index": null, "config": {}, "cardData": {"library_name": "coreml", "tags": ["vision", "feature-extraction", "dinov3", "coreml", "apple-silicon", "fp32"], "pipeline_tag": "feature-extraction"}, "siblings": [{"rfilename": ".gitattributes"}, {"rfilename": "LICENSE.md"}, {"rfilename": "README.md"}, {"rfilename": "benchmark_results.json"}, {"rfilename": "demo_image.png"}, {"rfilename": "dinov3_feature_comparison.png"}, {"rfilename": "dinov3_vits16_336x336_fp32.mlpackage/Data/com.apple.CoreML/model.mlmodel"}, {"rfilename": "dinov3_vits16_336x336_fp32.mlpackage/Data/com.apple.CoreML/weights/weight.bin"}, {"rfilename": "dinov3_vits16_336x336_fp32.mlpackage/Manifest.json"}], "spaces": [], "createdAt": "2025-11-04T00:19:51.000Z", "usedStorage": 87823797, "downloadsAllTime": 1, "inferenceProviderMapping": {}, "configJson": null, "onnxFiles": {}, "safetensorsSizeMb": 0.0, "approxSizeMb": 0.0, "fetchedAt": "2026-06-12T07:58:51.000Z"}