{"_id": "66a545691bade4bd85a9454f", "id": "onnx-models/LaBSE-onnx", "private": false, "pipeline_tag": "sentence-similarity", "library_name": "light-embed", "tags": ["light-embed", "onnx", "bert", "sentence-transformers", "feature-extraction", "sentence-similarity", "text-embeddings-inference", "endpoints_compatible", "region:us"], "downloads": 15, "likes": 1, "modelId": "onnx-models/LaBSE-onnx", "author": "onnx-models", "sha": "dee7c589dd7e6ec114d69ecf480330aa6cc49d38", "lastModified": "2024-07-27T19:21:23.000Z", "gated": false, "disabled": false, "mask_token": "[MASK]", "widgetData": [{"source_sentence": "That is a happy person", "sentences": ["That is a happy dog", "That is a very happy person", "Today is a sunny day"]}], "model-index": null, "config": {"architectures": ["BertModel"], "model_type": "bert", "tokenizer_config": {"cls_token": "[CLS]", "mask_token": "[MASK]", "pad_token": "[PAD]", "sep_token": "[SEP]", "unk_token": "[UNK]"}}, "cardData": {"library_name": "light-embed", "pipeline_tag": "sentence-similarity", "tags": ["sentence-transformers", "feature-extraction", "sentence-similarity"]}, "siblings": [{"rfilename": ".gitattributes"}, {"rfilename": "README.md"}, {"rfilename": "config.json"}, {"rfilename": "model.onnx"}, {"rfilename": "special_tokens_map.json"}, {"rfilename": "tokenizer.json"}, {"rfilename": "tokenizer_config.json"}, {"rfilename": "vocab.txt"}], "spaces": [], "createdAt": "2024-07-27T19:07:21.000Z", "usedStorage": 1897689862, "downloadsAllTime": 524, "inferenceProviderMapping": {}, "configJson": {"_name_or_path": "sentence-transformers/LaBSE", "architectures": ["BertModel"], "attention_probs_dropout_prob": 0.1, "directionality": "bidi", "gradient_checkpointing": false, "hidden_act": "gelu", "hidden_dropout_prob": 0.1, "hidden_size": 768, "initializer_range": 0.02, "intermediate_size": 3072, "layer_norm_eps": 1e-12, "max_position_embeddings": 512, "model_type": "bert", "num_attention_heads": 12, "num_hidden_layers": 12, "pad_token_id": 0, "pooler_fc_size": 768, "pooler_num_attention_heads": 12, "pooler_num_fc_layers": 3, "pooler_size_per_head": 128, "pooler_type": "first_token_transform", "position_embedding_type": "absolute", "transformers_version": "4.7.0", "type_vocab_size": 2, "use_cache": true, "vocab_size": 501153}, "onnxFiles": {"model.onnx": 1884.1}, "safetensorsSizeMb": 0.0, "approxSizeMb": 0.0, "fetchedAt": "2026-06-08T16:42:43.000Z"}