{"_id": "65496fa944e75a7de4ed55fe", "id": "phi0112358/paraphrase-MiniLM-L3-v2-GGML", "private": false, "pipeline_tag": "sentence-similarity", "library_name": "sentence-transformers", "tags": ["sentence-transformers", "feature-extraction", "sentence-similarity", "transformers", "dataset:flax-sentence-embeddings/stackexchange_xml", "dataset:s2orc", "dataset:ms_marco", "dataset:wiki_atomic_edits", "dataset:snli", "dataset:multi_nli", "dataset:embedding-data/altlex", "dataset:embedding-data/simple-wiki", "dataset:embedding-data/flickr30k-captions", "dataset:embedding-data/coco_captions", "dataset:embedding-data/sentence-compression", "dataset:embedding-data/QQP", "dataset:yahoo_answers_topics", "arxiv:1908.10084", "license:apache-2.0", "endpoints_compatible", "region:us"], "downloads": 0, "likes": 0, "modelId": "phi0112358/paraphrase-MiniLM-L3-v2-GGML", "author": "phi0112358", "sha": "599873066fbc3300ab35e5b46dd1d4317e0f5be6", "lastModified": "2023-11-06T23:02:17.000Z", "gated": false, "disabled": false, "widgetData": [{"source_sentence": "That is a happy person", "sentences": ["That is a happy dog", "That is a very happy person", "Today is a sunny day"]}], "model-index": null, "cardData": {"pipeline_tag": "sentence-similarity", "license": "apache-2.0", "tags": ["sentence-transformers", "feature-extraction", "sentence-similarity", "transformers"], "datasets": ["flax-sentence-embeddings/stackexchange_xml", "s2orc", "ms_marco", "wiki_atomic_edits", "snli", "multi_nli", "embedding-data/altlex", "embedding-data/simple-wiki", "embedding-data/flickr30k-captions", "embedding-data/coco_captions", "embedding-data/sentence-compression", "embedding-data/QQP", "yahoo_answers_topics"]}, "transformersInfo": {"auto_model": "AutoModel"}, "siblings": [{"rfilename": ".gitattributes"}, {"rfilename": "README.md"}, {"rfilename": "paraphrase-MiniLM-L3-v2-GGML-f16.bin"}, {"rfilename": "paraphrase-MiniLM-L3-v2-GGML-q4_0.bin"}, {"rfilename": "paraphrase-MiniLM-L3-v2-GGML-q4_1.bin"}], "spaces": [], "createdAt": "2023-11-06T22:58:49.000Z", "usedStorage": 56076069, "downloadsAllTime": 0, "inferenceProviderMapping": {}, "configJson": null, "onnxFiles": {}, "safetensorsSizeMb": 0.0, "approxSizeMb": 0.0, "fetchedAt": "2026-06-10T07:15:01.000Z"}