{"_id": "6919e25ce195942bdfdda848", "id": "Linhduongcute/nllf-medical-abstract", "private": false, "pipeline_tag": "feature-extraction", "library_name": "transformers", "tags": ["transformers", "safetensors", "bert", "feature-extraction", "arxiv:1910.09700", "endpoints_compatible", "region:us"], "downloads": 2, "likes": 0, "modelId": "Linhduongcute/nllf-medical-abstract", "author": "Linhduongcute", "sha": "a270a5284f1ad9e403786a230355dfb991c35bee", "lastModified": "2026-01-03T08:51:26.000Z", "gated": false, "disabled": false, "mask_token": "[MASK]", "model-index": null, "config": {"architectures": ["BertModel"], "model_type": "bert", "tokenizer_config": {"cls_token": "[CLS]", "mask_token": "[MASK]", "pad_token": "[PAD]", "sep_token": "[SEP]", "unk_token": "[UNK]"}}, "cardData": {"library_name": "transformers", "tags": []}, "transformersInfo": {"auto_model": "AutoModel", "pipeline_tag": "feature-extraction", "processor": "AutoTokenizer"}, "siblings": [{"rfilename": ".gitattributes"}, {"rfilename": "README.md"}, {"rfilename": "cls_layer.torch"}, {"rfilename": "config.json"}, {"rfilename": "merges.txt"}, {"rfilename": "model.safetensors"}, {"rfilename": "special_tokens_map.json"}, {"rfilename": "tokenizer_config.json"}, {"rfilename": "vocab.json"}, {"rfilename": "vocab.txt"}], "spaces": [], "createdAt": "2025-11-16T14:40:28.000Z", "safetensors": {"parameters": {"F32": 109482240}, "total": 109482240}, "usedStorage": 8829978632, "downloadsAllTime": 256, "inferenceProviderMapping": {}, "configJson": {"architectures": ["BertModel"], "attention_probs_dropout_prob": 0.1, "classifier_dropout": null, "gradient_checkpointing": false, "hidden_act": "gelu", "hidden_dropout_prob": 0.1, "hidden_size": 768, "initializer_range": 0.02, "intermediate_size": 3072, "layer_norm_eps": 1e-12, "max_position_embeddings": 512, "model_type": "bert", "num_attention_heads": 12, "num_hidden_layers": 12, "pad_token_id": 0, "position_embedding_type": "absolute", "torch_dtype": "float32", "transformers_version": "4.53.3", "type_vocab_size": 2, "use_cache": true, "vocab_size": 30522}, "onnxFiles": {}, "safetensorsSizeMb": 438.0, "approxSizeMb": 437.9, "fetchedAt": "2026-06-12T07:58:51.000Z"}