{"_id": "66ebcb8a9e161a88481ca01a", "id": "minhquy1624/model_gam_1709_final", "private": false, "pipeline_tag": "feature-extraction", "library_name": "transformers", "tags": ["transformers", "safetensors", "xlm-roberta", "feature-extraction", "arxiv:1910.09700", "text-embeddings-inference", "endpoints_compatible", "region:us"], "downloads": 1, "likes": 0, "modelId": "minhquy1624/model_gam_1709_final", "author": "minhquy1624", "sha": "53709461804a98430abc62e35d9d9a71785f6991", "lastModified": "2024-09-19T07:00:47.000Z", "gated": false, "disabled": false, "mask_token": "<mask>", "model-index": null, "config": {"architectures": ["XLMRobertaModel"], "model_type": "xlm-roberta", "tokenizer_config": {"bos_token": "<s>", "cls_token": "<s>", "eos_token": "</s>", "mask_token": "<mask>", "pad_token": "<pad>", "sep_token": "</s>", "unk_token": "<unk>"}}, "cardData": {"library_name": "transformers", "tags": []}, "transformersInfo": {"auto_model": "AutoModelForMultimodalLM", "pipeline_tag": "feature-extraction", "processor": "AutoTokenizer"}, "siblings": [{"rfilename": ".gitattributes"}, {"rfilename": "README.md"}, {"rfilename": "config.json"}, {"rfilename": "model.safetensors"}, {"rfilename": "special_tokens_map.json"}, {"rfilename": "tokenizer.json"}, {"rfilename": "tokenizer_config.json"}], "spaces": [], "createdAt": "2024-09-19T06:58:18.000Z", "safetensors": {"parameters": {"F32": 559890432}, "total": 559890432}, "usedStorage": 2256690008, "downloadsAllTime": 2, "inferenceProviderMapping": {}, "configJson": {"_name_or_path": "/workspace/nmquy/GHTK/GAM/example/model_1709", "architectures": ["XLMRobertaModel"], "attention_probs_dropout_prob": 0.1, "bos_token_id": 0, "classifier_dropout": null, "eos_token_id": 2, "hidden_act": "gelu", "hidden_dropout_prob": 0.1, "hidden_size": 1024, "id2label": {"0": "O", "1": "Sản phẩm", "2": "Địa chỉ nhận hàng", "3": "Số lượng sản phẩm", "4": "Đặc điểm khác của da", "5": "Đơn vị sản phẩm", "6": "Dáng người", "7": "Phong cách mua sắm", "8": "Màu sắc sản phẩm", "9": "Màu da", "10": "Thời gian nhận hàng", "11": "Cân nặng khách hàng", "12": "Chất tóc", "13": "Phong cách thời trang", "14": "Phong cách nhà cửa", "15": "Cung mệnh", "16": "Cung hoàng đạo", "17": "Loại da", "18": "Độ tuổi khách hàng", "19": "Số điện thoại nhận hàng", "20": "Giá sản phẩm", "21": "Dáng khuôn mặt", "22": "Độ dài tóc", "23": "Mật độ tóc", "24": "Chiều cao khách hàng", "25": "Mã sản phẩm", "26": "Khối lượng sản phẩm", "27": "Số đo vòng", "28": "Chiều dài sản phẩm", "29": "Chiều rộng sản phẩm"}, "initializer_range": 0.02, "intermediate_size": 4096, "label2id": {"Chiều cao khách hàng": 24, "Chiều dài sản phẩm": 28, "Chiều rộng sản phẩm": 29, "Chất tóc": 12, "Cung hoàng đạo": 16, "Cung mệnh": 15, "Cân nặng khách hàng": 11, "Dáng khuôn mặt": 21, "Dáng người": 6, "Giá sản phẩm": 20, "Khối lượng sản phẩm": 26, "Loại da": 17, "Màu da": 9, "Màu sắc sản phẩm": 8, "Mã sản phẩm": 25, "Mật độ tóc": 23, "O": 0, "Phong cách mua sắm": 7, "Phong cách nhà cửa": 14, "Phong cách thời trang": 13, "Sản phẩm": 1, "Số lượng sản phẩm": 3, "Số điện thoại nhận hàng": 19, "Số đo vòng": 27, "Thời gian nhận hàng": 10, "Đơn vị sản phẩm": 5, "Đặc điểm khác của da": 4, "Địa chỉ nhận hàng": 2, "Độ dài tóc": 22, "Độ tuổi khách hàng": 18}, "layer_norm_eps": 1e-05, "max_position_embeddings": 514, "model_type": "xlm-roberta", "num_attention_heads": 16, "num_hidden_layers": 24, "output_past": true, "pad_token_id": 1, "position_embedding_type": "absolute", "torch_dtype": "float32", "transformers_version": "4.44.2", "type_vocab_size": 1, "use_cache": true, "vocab_size": 250002}, "onnxFiles": {}, "safetensorsSizeMb": 2239.6, "approxSizeMb": 2239.6, "fetchedAt": "2026-06-12T07:58:51.000Z"}