{"_id": "6955a704df172c4fd92f71a6", "id": "KentStone/Holographic_Neural_Mesh", "private": false, "pipeline_tag": "feature-extraction", "library_name": "numpy", "tags": ["numpy", "vector-symbolic-architecture", "holographic-reduced-representations", "sparse-distributed-memory", "semantic-hashing", "cognitive-architecture", "memory-systems", "no-gpu", "feature-extraction", "en", "region:us"], "downloads": 0, "likes": 0, "modelId": "KentStone/Holographic_Neural_Mesh", "author": "KentStone", "sha": "4a295f773af96a410859166b987686e97035dc64", "lastModified": "2025-12-31T23:03:53.000Z", "gated": false, "disabled": false, "model-index": null, "config": {}, "cardData": {"language": "en", "tags": ["vector-symbolic-architecture", "holographic-reduced-representations", "sparse-distributed-memory", "semantic-hashing", "cognitive-architecture", "memory-systems", "no-gpu"], "library_name": "numpy", "pipeline_tag": "feature-extraction"}, "siblings": [{"rfilename": ".gitattributes"}, {"rfilename": "README.md"}, {"rfilename": "hnm_v3.py"}, {"rfilename": "industry_benchmark.py"}], "spaces": [], "createdAt": "2025-12-31T22:43:16.000Z", "usedStorage": 0, "downloadsAllTime": 0, "inferenceProviderMapping": {}, "configJson": null, "onnxFiles": {}, "safetensorsSizeMb": 0.0, "approxSizeMb": 0.0, "fetchedAt": "2026-06-12T07:58:51.000Z"}