{"_id": "68412d1030231eddbe68c780", "id": "pasukka/synonyms_v2", "private": false, "pipeline_tag": "sentence-similarity", "library_name": "sentence-transformers", "tags": ["sentence-transformers", "safetensors", "bert", "sentence-similarity", "feature-extraction", "generated_from_trainer", "dataset_size:21056", "loss:ContrastiveLoss", "arxiv:1908.10084", "base_model:ai-forever/ruBert-base", "base_model:finetune:ai-forever/ruBert-base", "text-embeddings-inference", "endpoints_compatible", "region:us"], "downloads": 3, "likes": 0, "modelId": "pasukka/synonyms_v2", "author": "pasukka", "sha": "2b0de91933467c296b61845c7012147c70f367ca", "lastModified": "2025-06-05T05:37:51.000Z", "gated": false, "disabled": false, "mask_token": "[MASK]", "widgetData": [{"source_sentence": "фильтр топливный с отстойником", "sentences": ["прокладка-уплотнитель поддона картера", "ручка кпп с кнопкой", "элемент топливный с отстойником"]}, {"source_sentence": "провода датчика кислорода", "sentences": ["салонный элемент с hepa элементом", "гидроусилитель рулевого управления", "compressor кондиционера"]}, {"source_sentence": "фильтр воздушный салонный", "sentences": ["масляный радиатор двигателя", "газовый трос с наконечниками и кожухом", "освещение салона"]}, {"source_sentence": "шланг отопителя салона", "sentences": ["температурный sensor радиатора", "грубый fuel filter", "зажигательная искровая свеча"]}, {"source_sentence": "элемент стабилизатора", "sentences": ["измеритель давления топлива", "карб", "узел стабилизатора"]}], "model-index": null, "config": {"architectures": ["BertModel"], "model_type": "bert", "tokenizer_config": {"cls_token": "[CLS]", "mask_token": "[MASK]", "pad_token": "[PAD]", "sep_token": "[SEP]", "unk_token": "[UNK]"}}, "cardData": {"tags": ["sentence-transformers", "sentence-similarity", "feature-extraction", "generated_from_trainer", "dataset_size:21056", "loss:ContrastiveLoss"], "base_model": "ai-forever/ruBert-base", "widget": [{"source_sentence": "фильтр топливный с отстойником", "sentences": ["прокладка-уплотнитель поддона картера", "ручка кпп с кнопкой", "элемент топливный с отстойником"]}, {"source_sentence": "провода датчика кислорода", "sentences": ["салонный элемент с hepa элементом", "гидроусилитель рулевого управления", "compressor кондиционера"]}, {"source_sentence": "фильтр воздушный салонный", "sentences": ["масляный радиатор двигателя", "газовый трос с наконечниками и кожухом", "освещение салона"]}, {"source_sentence": "шланг отопителя салона", "sentences": ["температурный sensor радиатора", "грубый fuel filter", "зажигательная искровая свеча"]}, {"source_sentence": "элемент стабилизатора", "sentences": ["измеритель давления топлива", "карб", "узел стабилизатора"]}], "pipeline_tag": "sentence-similarity", "library_name": "sentence-transformers"}, "siblings": [{"rfilename": ".gitattributes"}, {"rfilename": "1_Pooling/config.json"}, {"rfilename": "README.md"}, {"rfilename": "config.json"}, {"rfilename": "config_sentence_transformers.json"}, {"rfilename": "model.safetensors"}, {"rfilename": "modules.json"}, {"rfilename": "sentence_bert_config.json"}, {"rfilename": "special_tokens_map.json"}, {"rfilename": "tokenizer.json"}, {"rfilename": "tokenizer_config.json"}, {"rfilename": "vocab.txt"}], "spaces": [], "createdAt": "2025-06-05T05:37:20.000Z", "safetensors": {"parameters": {"F32": 178307328}, "total": 178307328}, "usedStorage": 713251688, "downloadsAllTime": 40, "inferenceProviderMapping": {}, "configJson": {"architectures": ["BertModel"], "attention_probs_dropout_prob": 0.1, "classifier_dropout": null, "directionality": "bidi", "hidden_act": "gelu", "hidden_dropout_prob": 0.1, "hidden_size": 768, "initializer_range": 0.02, "intermediate_size": 3072, "layer_norm_eps": 1e-12, "max_position_embeddings": 512, "model_type": "bert", "num_attention_heads": 12, "num_hidden_layers": 12, "pad_token_id": 0, "pooler_fc_size": 768, "pooler_num_attention_heads": 12, "pooler_num_fc_layers": 3, "pooler_size_per_head": 128, "pooler_type": "first_token_transform", "position_embedding_type": "absolute", "torch_dtype": "float32", "transformers_version": "4.52.3", "type_vocab_size": 2, "use_cache": true, "vocab_size": 120138}, "onnxFiles": {}, "safetensorsSizeMb": 713.3, "approxSizeMb": 713.2, "fetchedAt": "2026-06-09T06:55:53.000Z"}