{"_id": "668c9f40af57d6e4b52e8136", "id": "LeoChiuu/all-MiniLM-L6-v2-negations", "private": false, "pipeline_tag": "sentence-similarity", "library_name": "sentence-transformers", "tags": ["sentence-transformers", "safetensors", "bert", "sentence-similarity", "feature-extraction", "generated_from_trainer", "dataset_size:77376", "loss:CosineSimilarityLoss", "arxiv:1908.10084", "base_model:sentence-transformers/all-MiniLM-L6-v2", "base_model:finetune:sentence-transformers/all-MiniLM-L6-v2", "text-embeddings-inference", "endpoints_compatible", "region:us"], "downloads": 6, "likes": 0, "modelId": "LeoChiuu/all-MiniLM-L6-v2-negations", "author": "LeoChiuu", "sha": "68453ee84d21c42eb12f31bdc0ca8b89047abcaa", "lastModified": "2024-07-10T02:57:19.000Z", "gated": false, "disabled": false, "mask_token": "[MASK]", "widgetData": [{"source_sentence": "He has published several books on nutrition, trace metals but not biochemistry imbalances.", "sentences": ["This in turn can help in effective communication between healthcare providers and their patients.", "He has written several books on nutrition, trace metals, and biochemistry imbalances.", "One of the most boring movies I have ever seen."]}, {"source_sentence": "She was denied the 2011 NSK Neustadt Prize for Children's Literature.", "sentences": ["She was the recipient of the 2011 NSK Neustadt Prize for Children's Literature.", "The ancient woodland at Dickshills is also located here.", "An element (such as a tree) that contributes to evapotranspiration can be called an evapotranspirator."]}, {"source_sentence": "Viking, after the resemblance the pitchers bear to the prow of a Viking ship.", "sentences": ["Viking, after the striking difference the pitchers bear to the prow of a Viking ship.", "Honshu is formed from the island arcs.", "For instance, even alcohol consumption by a pregnant woman is unable to lead to fetal alcohol syndrome."]}, {"source_sentence": "Logging has not been undertake near the headwaters of the creek.", "sentences": ["Then I had to continue pairing it periodically since it somehow kept dropping.", "That's fair, Nance.", "Logging has been done near the headwaters of the creek."]}, {"source_sentence": "He published a history of Cornwall, New York in 1873.", "sentences": ["He failed to publish a history of Cornwall, New York in 1873.", "Salafis assert that reliance on taqlid has led to Islam 's decline.", "Lot of holes in the plot: there's nothing about how he became the emperor; nothing about where he spend 20 years between his childhood and mature age."]}], "model-index": null, "config": {"architectures": ["BertModel"], "model_type": "bert", "tokenizer_config": {"cls_token": "[CLS]", "mask_token": "[MASK]", "pad_token": "[PAD]", "sep_token": "[SEP]", "unk_token": "[UNK]"}}, "cardData": {"language": [], "library_name": "sentence-transformers", "tags": ["sentence-transformers", "sentence-similarity", "feature-extraction", "generated_from_trainer", "dataset_size:77376", "loss:CosineSimilarityLoss"], "base_model": "sentence-transformers/all-MiniLM-L6-v2", "datasets": [], "widget": [{"source_sentence": "He has published several books on nutrition, trace metals but not biochemistry imbalances.", "sentences": ["This in turn can help in effective communication between healthcare providers and their patients.", "He has written several books on nutrition, trace metals, and biochemistry imbalances.", "One of the most boring movies I have ever seen."]}, {"source_sentence": "She was denied the 2011 NSK Neustadt Prize for Children's Literature.", "sentences": ["She was the recipient of the 2011 NSK Neustadt Prize for Children's Literature.", "The ancient woodland at Dickshills is also located here.", "An element (such as a tree) that contributes to evapotranspiration can be called an evapotranspirator."]}, {"source_sentence": "Viking, after the resemblance the pitchers bear to the prow of a Viking ship.", "sentences": ["Viking, after the striking difference the pitchers bear to the prow of a Viking ship.", "Honshu is formed from the island arcs.", "For instance, even alcohol consumption by a pregnant woman is unable to lead to fetal alcohol syndrome."]}, {"source_sentence": "Logging has not been undertake near the headwaters of the creek.", "sentences": ["Then I had to continue pairing it periodically since it somehow kept dropping.", "That's fair, Nance.", "Logging has been done near the headwaters of the creek."]}, {"source_sentence": "He published a history of Cornwall, New York in 1873.", "sentences": ["He failed to publish a history of Cornwall, New York in 1873.", "Salafis assert that reliance on taqlid has led to Islam 's decline.", "Lot of holes in the plot: there's nothing about how he became the emperor; nothing about where he spend 20 years between his childhood and mature age."]}], "pipeline_tag": "sentence-similarity"}, "siblings": [{"rfilename": ".gitattributes"}, {"rfilename": "1_Pooling/config.json"}, {"rfilename": "README.md"}, {"rfilename": "config.json"}, {"rfilename": "config_sentence_transformers.json"}, {"rfilename": "model.safetensors"}, {"rfilename": "modules.json"}, {"rfilename": "sentence_bert_config.json"}, {"rfilename": "special_tokens_map.json"}, {"rfilename": "tokenizer.json"}, {"rfilename": "tokenizer_config.json"}, {"rfilename": "vocab.txt"}], "spaces": [], "createdAt": "2024-07-09T02:24:00.000Z", "safetensors": {"parameters": {"F32": 22713216}, "total": 22713216}, "usedStorage": 454320960, "downloadsAllTime": 11, "inferenceProviderMapping": {}, "configJson": {"_name_or_path": "sentence-transformers/all-MiniLM-L6-v2", "architectures": ["BertModel"], "attention_probs_dropout_prob": 0.1, "classifier_dropout": null, "gradient_checkpointing": false, "hidden_act": "gelu", "hidden_dropout_prob": 0.1, "hidden_size": 384, "initializer_range": 0.02, "intermediate_size": 1536, "layer_norm_eps": 1e-12, "max_position_embeddings": 512, "model_type": "bert", "num_attention_heads": 12, "num_hidden_layers": 6, "pad_token_id": 0, "position_embedding_type": "absolute", "torch_dtype": "float32", "transformers_version": "4.40.2", "type_vocab_size": 2, "use_cache": true, "vocab_size": 30522}, "onnxFiles": {}, "safetensorsSizeMb": 90.9, "approxSizeMb": 90.9, "fetchedAt": "2026-06-09T06:55:53.000Z"}