{"_id": "685aec70fc78e58f17aa03c0", "id": "stevenbucaille/disk", "private": false, "pipeline_tag": "feature-extraction", "library_name": "transformers", "tags": ["transformers", "safetensors", "disk", "feature-extraction", "custom_code", "arxiv:1910.09700", "region:us"], "downloads": 413, "likes": 1, "modelId": "stevenbucaille/disk", "author": "stevenbucaille", "sha": "48728d39bffb350a19b9114531e56b59e87b14fd", "lastModified": "2025-07-07T12:13:04.000Z", "gated": false, "disabled": false, "model-index": null, "config": {"architectures": ["DiskForKeypointDetection"], "auto_map": {"AutoConfig": "configuration_disk.DiskConfig", "AutoModelForKeypointDetection": "modeling_disk.DiskForKeypointDetection"}, "model_type": "disk"}, "cardData": {"library_name": "transformers", "tags": []}, "transformersInfo": {"auto_model": "AutoModelForKeypointDetection", "custom_class": "modeling_disk.DiskForKeypointDetection", "pipeline_tag": "feature-extraction"}, "siblings": [{"rfilename": ".gitattributes"}, {"rfilename": ".gitignore"}, {"rfilename": "README.md"}, {"rfilename": "config.json"}, {"rfilename": "configuration_disk.py"}, {"rfilename": "model.safetensors"}, {"rfilename": "modeling_disk.py"}, {"rfilename": "preprocessor_config.json"}], "spaces": [], "createdAt": "2025-06-24T18:20:32.000Z", "safetensors": {"parameters": {"F32": 1092369}, "total": 1092369}, "usedStorage": 8744112, "downloadsAllTime": 98116, "inferenceProviderMapping": {}, "configJson": {"architectures": ["DiskForKeypointDetection"], "auto_map": {"AutoConfig": "configuration_disk.DiskConfig", "AutoModelForKeypointDetection": "modeling_disk.DiskForKeypointDetection"}, "descriptor_decoder_dim": 128, "detection_threshold": 0.0, "max_num_keypoints": null, "model_type": "disk", "nms_window_size": 5, "pad_if_not_divisible": true, "torch_dtype": "float32", "transformers_version": "4.54.0.dev0", "weights": "depth"}, "onnxFiles": {}, "safetensorsSizeMb": 4.4, "approxSizeMb": 4.4, "fetchedAt": "2026-06-08T13:32:59.000Z"}