{"_id": "67ff574d5c9705fa3b934d47", "id": "mradermacher/e5-large-unsupervised-GGUF", "private": false, "pipeline_tag": "sentence-similarity", "library_name": "transformers", "tags": ["transformers", "gguf", "Sentence Transformers", "sentence-similarity", "sentence-transformers", "en", "base_model:intfloat/e5-large-unsupervised", "base_model:quantized:intfloat/e5-large-unsupervised", "license:mit", "endpoints_compatible", "region:us", "feature-extraction"], "downloads": 166, "likes": 0, "modelId": "mradermacher/e5-large-unsupervised-GGUF", "author": "mradermacher", "sha": "f96052c783024c419fc299ab2c409e3921e3f7fa", "lastModified": "2025-07-11T05:28:20.000Z", "gated": false, "disabled": false, "widgetData": [{"source_sentence": "That is a happy person", "sentences": ["That is a happy dog", "That is a very happy person", "Today is a sunny day"]}], "model-index": null, "config": {}, "cardData": {"base_model": "intfloat/e5-large-unsupervised", "language": ["en"], "library_name": "transformers", "license": "mit", "mradermacher": {"readme_rev": 1}, "quantized_by": "mradermacher", "tags": ["Sentence Transformers", "sentence-similarity", "sentence-transformers"]}, "transformersInfo": {"auto_model": "AutoModel"}, "gguf": {"total": 334092288, "architecture": "bert", "context_length": 512, "causal": false, "totalFileSize": 670530976}, "siblings": [{"rfilename": ".gitattributes"}, {"rfilename": "README.md"}, {"rfilename": "e5-large-unsupervised.IQ4_XS.gguf"}, {"rfilename": "e5-large-unsupervised.Q2_K.gguf"}, {"rfilename": "e5-large-unsupervised.Q3_K_L.gguf"}, {"rfilename": "e5-large-unsupervised.Q3_K_M.gguf"}, {"rfilename": "e5-large-unsupervised.Q3_K_S.gguf"}, {"rfilename": "e5-large-unsupervised.Q4_K_M.gguf"}, {"rfilename": "e5-large-unsupervised.Q4_K_S.gguf"}, {"rfilename": "e5-large-unsupervised.Q5_K_M.gguf"}, {"rfilename": "e5-large-unsupervised.Q5_K_S.gguf"}, {"rfilename": "e5-large-unsupervised.Q6_K.gguf"}, {"rfilename": "e5-large-unsupervised.Q8_0.gguf"}, {"rfilename": "e5-large-unsupervised.f16.gguf"}], "spaces": [], "createdAt": "2025-04-16T07:07:57.000Z", "usedStorage": 3080702400, "downloadsAllTime": 1110, "inferenceProviderMapping": {}, "configJson": null, "onnxFiles": {}, "safetensorsSizeMb": 0.0, "approxSizeMb": 0.0, "fetchedAt": "2026-06-08T13:32:59.000Z"}