{"_id": "63a5a5bd062d8d60ff7b3515", "id": "lang-uk/fasttext_uk_cbow", "private": false, "pipeline_tag": "feature-extraction", "library_name": "generic", "tags": ["generic", "feature-extraction", "dataset:ubertext2.0", "license:mit", "region:us"], "downloads": 0, "likes": 1, "modelId": "lang-uk/fasttext_uk_cbow", "author": "lang-uk", "sha": "a90342a536354d15693f0fee313664f1ef5ba105", "lastModified": "2023-03-28T11:00:39.000Z", "gated": false, "disabled": false, "widgetData": [{"text": "доброго вечора ми з україни"}], "model-index": null, "cardData": {"license": "mit", "tags": ["feature-extraction"], "library_name": "generic", "datasets": ["ubertext2.0"], "widget": [{"text": "доброго вечора ми з україни"}]}, "siblings": [{"rfilename": ".gitattributes"}, {"rfilename": "README.md"}, {"rfilename": "cbow.uk.300.bin"}, {"rfilename": "pipeline.py"}, {"rfilename": "requirements.txt"}], "spaces": [], "createdAt": "2022-12-23T12:57:33.000Z", "usedStorage": 8866515197, "downloadsAllTime": 0, "inferenceProviderMapping": {}, "configJson": null, "onnxFiles": {}, "safetensorsSizeMb": 0.0, "approxSizeMb": 0.0, "fetchedAt": "2026-06-12T07:58:51.000Z"}