{"_id": "666b30bd475d0f8c1b2769b4", "id": "Qdrant/bm25", "private": false, "pipeline_tag": "sentence-similarity", "library_name": "transformers", "tags": ["transformers", "sentence-similarity", "en", "license:apache-2.0", "endpoints_compatible", "deploy:azure", "region:us"], "downloads": 626712, "likes": 32, "modelId": "Qdrant/bm25", "author": "Qdrant", "sha": "e499a1f8d6bec960aab5533a0941bf914e70faf9", "lastModified": "2025-01-20T17:35:08.000Z", "gated": false, "disabled": false, "widgetData": [{"source_sentence": "That is a happy person", "sentences": ["That is a happy dog", "That is a very happy person", "Today is a sunny day"]}], "model-index": null, "config": {}, "cardData": {"license": "apache-2.0", "language": ["en"], "pipeline_tag": "sentence-similarity"}, "transformersInfo": {"auto_model": "AutoModel"}, "siblings": [{"rfilename": ".gitattributes"}, {"rfilename": "README.md"}, {"rfilename": "arabic.txt"}, {"rfilename": "azerbaijani.txt"}, {"rfilename": "basque.txt"}, {"rfilename": "bengali.txt"}, {"rfilename": "catalan.txt"}, {"rfilename": "chinese.txt"}, {"rfilename": "config.json"}, {"rfilename": "danish.txt"}, {"rfilename": "dutch.txt"}, {"rfilename": "english.txt"}, {"rfilename": "finnish.txt"}, {"rfilename": "french.txt"}, {"rfilename": "german.txt"}, {"rfilename": "greek.txt"}, {"rfilename": "hebrew.txt"}, {"rfilename": "hinglish.txt"}, {"rfilename": "hungarian.txt"}, {"rfilename": "indonesian.txt"}, {"rfilename": "italian.txt"}, {"rfilename": "kazakh.txt"}, {"rfilename": "nepali.txt"}, {"rfilename": "norwegian.txt"}, {"rfilename": "portuguese.txt"}, {"rfilename": "romanian.txt"}, {"rfilename": "russian.txt"}, {"rfilename": "slovene.txt"}, {"rfilename": "spanish.txt"}, {"rfilename": "stopwords.txt"}, {"rfilename": "swedish.txt"}, {"rfilename": "tajik.txt"}, {"rfilename": "turkish.txt"}], "spaces": ["vietfinn9/medical-ai-chatbot-backend", "Raghav-1729/diablo-ai-agent", "sadaisystems/sdmrec-docker", "nurudeen8/rag-fortress", "ai-department-lpnu/scientific-rag", "zaitsev-e-a/school21-lpk-ai-helper", "arjun10g/bankmind", "mcikalmerdeka/adaptive-rag", "techconspartners/ConversAI", "techconspartners/aQ0m6txMCzU5xB356d4Xf169WSHkrJC", "mtesmer-iqnox/sss", "puzan789/jorpier", "puzan8932/Project", "tabesink92/Mg_Alloy_Knowledgebase_v2", "jonathanjordan21/Qdrant-knowledge", "AlexFoxalt/mio-rag-playground-v0", "AlekseyV/sparseembed", "1awrance/law_vn", "26tanishabanik/fir-case-management", "srivatsavdamaraju/mvp_2_hf_dev_clone", "IndraneelKumar/Search_Engine", "srivatsavdamaraju/mvp__hf_dev_aws", "srivatsavdamaraju2/dev_mvp", "Rauhan/AgenticDataPipeline", "JediOfZorr/fieldasisstant", "ZQliu1999/agentic-rag-portfolio", "DjebelV/Gradio_App_rag_for_noob", "botInfinity/NEPAL_Constitution_Assistant_AI", "amiramedhat/hr-agent-demo", "rikodon72/odyssey-rag", "Mint1456/test_space", "tusharmishra288/legisyukti-rag-engine", "1337XCode/personabot-api", "shashi-hue/rag-kyc", "Fardeen1004/rag-backend", "chmielvu/jina-code-embed-bm25-rerank", "tanmaivan/hutmind", "emxeluxe/carryofy_bot", "yongnyong/rag_nammigo", "prabhal/geneseek", "OussemaHassine/RAG_HF", "Aman045/openenv-search-rl", "zaitsev-e-a/test_center_ai", "welcometoFightclub/acpc_backend_second", "Shwrma/Nandly_backend", "welcometoFightclub/acpc_testing_third", "Stoic-2910/acpc-testing-third", "maanavchellani/CODECHAT", "JediOfZorr/ragfield", "welcometoFightclub/acpc_rag_testing3", "welcometoFightclub/acpc_rag_testing-4", "emxeluxe/chatpdf", "welcometoFightclub/acpc-testing-5", "AlshimaaAhmed/Startups_Embedding_and_uploadingTO_VDB", "chmielvu/Fast_Text-BM25-Rerank", "chmielvu/jina-code-embed-bm25-rerank2", "chmielvu/jina-code-embed-bm25-rerank3", "chmielvu/jina-code-embed-bm25-rerank4", "Kamol7774/rag-demo", "heinkehihn/SemanticSearchWorkshop", "dynamodenis254/docu-search", "tiramesu55/powerintel", "bakhil-aissa/RAG", "adityanandkishor/mitra-mvp-chatbot", "aeolusyansheng/qdrant-knowledge-base", "YogPandya/personal-rag-backend", "acesmile/toursim_chatbot", "binarybhakt/citepdf", "anhkhoiphan/092_agent_api", "Nicholas-Nevan-Kurniawan/Arxiv-rag", "Jbbok/v5-ui", "Patrick2002-de/annex-backend", "mksm-ai/constitution-civil-code-rag-qa", "emxelux/chatmypdf", "anhdan/questioning-demo", "Meshyboi/TigerGraph-Hack", "hanabi12233/oil-pq-backend", "AdarshRL/medical-diagnostic-rag-dashboard", "vgguerra/OpenEnergy", "Jbbok/v5-rag-be", "anindita23b/shopping-assistant-api", "mdubs28/curio", "UDHOV/production-rag-backend", "Jbbok/SEC-Agent", "adityanandkishor/mitra_mvp_two", "fady-50/AI-agent", "PratikKansara/ai-system-design-copilot", "anhkhoiphan/rag_project_backend", "LightRT/pdf_rag", "LightRT/text2sql_backend", "Turab0104/scaler-backend"], "createdAt": "2024-06-13T17:47:41.000Z", "usedStorage": 0, "downloadsAllTime": 5670849, "inferenceProviderMapping": {}, "configJson": {}, "onnxFiles": {}, "safetensorsSizeMb": 0.0, "approxSizeMb": 0.0, "fetchedAt": "2026-06-08T00:55:47.000Z"}