{"_id": "677f5f3a2c09182b6c1bb2e3", "id": "Jiayi-Private/tt", "private": false, "pipeline_tag": "feature-extraction", "library_name": "transformers", "tags": ["transformers", "safetensors", "gpt2", "feature-extraction", "arxiv:1910.09700", "endpoints_compatible", "region:us"], "downloads": 5, "likes": 0, "modelId": "Jiayi-Private/tt", "author": "Jiayi-Private", "sha": "dbdaeab1b0854d9350e35fe7d13d021178b3372e", "lastModified": "2025-01-09T05:31:53.000Z", "gated": false, "disabled": false, "model-index": null, "config": {"architectures": ["GPT2Model"], "model_type": "gpt2"}, "cardData": {"library_name": "transformers", "tags": []}, "transformersInfo": {"auto_model": "AutoModel", "pipeline_tag": "feature-extraction", "processor": "AutoTokenizer"}, "siblings": [{"rfilename": ".gitattributes"}, {"rfilename": "README.md"}, {"rfilename": "config.json"}, {"rfilename": "model.safetensors"}], "spaces": [], "createdAt": "2025-01-09T05:31:38.000Z", "safetensors": {"parameters": {"F32": 124439808}, "total": 124439808}, "usedStorage": 497772416, "downloadsAllTime": 10, "inferenceProviderMapping": {}, "configJson": {"activation_function": "gelu_new", "architectures": ["GPT2Model"], "attn_pdrop": 0.1, "bos_token_id": 50256, "embd_pdrop": 0.1, "eos_token_id": 50256, "initializer_range": 0.02, "layer_norm_epsilon": 1e-05, "model_type": "gpt2", "n_ctx": 1024, "n_embd": 768, "n_head": 12, "n_inner": null, "n_layer": 12, "n_positions": 1024, "reorder_and_upcast_attn": false, "resid_pdrop": 0.1, "scale_attn_by_inverse_layer_idx": false, "scale_attn_weights": true, "summary_activation": null, "summary_first_dropout": 0.1, "summary_proj_to_labels": true, "summary_type": "cls_index", "summary_use_proj": true, "task_specific_params": {"text-generation": {"do_sample": true, "max_length": 50}}, "transformers_version": "4.47.1", "use_cache": true, "vocab_size": 50257}, "onnxFiles": {}, "safetensorsSizeMb": 497.8, "approxSizeMb": 497.8, "fetchedAt": "2026-06-11T08:11:04.000Z"}