{"_id": "67b962f4160a98c76959d71e", "id": "mradermacher/minilm-L12-H384-psychology-GGUF", "private": false, "pipeline_tag": "feature-extraction", "library_name": "transformers", "tags": ["transformers", "gguf", "sentence-transformers", "sentence-similarity", "feature-extraction", "generated_from_trainer", "dataset_size:2402", "loss:TripletLoss", "en", "base_model:jtatman/minilm-L12-H384-psychology", "base_model:quantized:jtatman/minilm-L12-H384-psychology", "endpoints_compatible", "region:us"], "downloads": 62, "likes": 0, "modelId": "mradermacher/minilm-L12-H384-psychology-GGUF", "author": "mradermacher", "sha": "a51f8335bfd7029fb635c0a08aab5d330fb88cb7", "lastModified": "2025-02-22T05:39:42.000Z", "gated": false, "disabled": false, "model-index": null, "config": {}, "cardData": {"base_model": "jtatman/minilm-L12-H384-psychology", "language": ["en"], "library_name": "transformers", "quantized_by": "mradermacher", "tags": ["sentence-transformers", "sentence-similarity", "feature-extraction", "generated_from_trainer", "dataset_size:2402", "loss:TripletLoss"]}, "transformersInfo": {"auto_model": "AutoModel"}, "gguf": {"total": 33212160, "architecture": "bert", "context_length": 512, "causal": false, "totalFileSize": 67580288}, "siblings": [{"rfilename": ".gitattributes"}, {"rfilename": "README.md"}, {"rfilename": "minilm-L12-H384-psychology.IQ4_XS.gguf"}, {"rfilename": "minilm-L12-H384-psychology.Q2_K.gguf"}, {"rfilename": "minilm-L12-H384-psychology.Q3_K_L.gguf"}, {"rfilename": "minilm-L12-H384-psychology.Q3_K_M.gguf"}, {"rfilename": "minilm-L12-H384-psychology.Q3_K_S.gguf"}, {"rfilename": "minilm-L12-H384-psychology.Q4_K_M.gguf"}, {"rfilename": "minilm-L12-H384-psychology.Q4_K_S.gguf"}, {"rfilename": "minilm-L12-H384-psychology.Q5_K_M.gguf"}, {"rfilename": "minilm-L12-H384-psychology.Q5_K_S.gguf"}, {"rfilename": "minilm-L12-H384-psychology.Q6_K.gguf"}, {"rfilename": "minilm-L12-H384-psychology.Q8_0.gguf"}, {"rfilename": "minilm-L12-H384-psychology.f16.gguf"}], "spaces": [], "createdAt": "2025-02-22T05:39:00.000Z", "usedStorage": 386576768, "downloadsAllTime": 1103, "inferenceProviderMapping": {}, "configJson": null, "onnxFiles": {}, "safetensorsSizeMb": 0.0, "approxSizeMb": 0.0, "fetchedAt": "2026-06-09T22:07:05.000Z"}