{"_id": "68a74c500c71c3e19a245cc0", "id": "pa-shk/USER-bge-m3", "private": false, "pipeline_tag": "sentence-similarity", "library_name": "sentence-transformers", "tags": ["sentence-transformers", "safetensors", "xlm-roberta", "sentence-similarity", "feature-extraction", "dense", "generated_from_trainer", "dataset_size:19210", "loss:CoSENTLoss", "arxiv:1908.10084", "base_model:deepvk/USER-bge-m3", "base_model:finetune:deepvk/USER-bge-m3", "text-embeddings-inference", "endpoints_compatible", "region:us"], "downloads": 3, "likes": 1, "modelId": "pa-shk/USER-bge-m3", "author": "pa-shk", "sha": "4ecbea4431a2293609c9200f11319ac384b7e14c", "lastModified": "2025-08-21T19:27:27.000Z", "gated": false, "disabled": false, "mask_token": "<mask>", "widgetData": [{"source_sentence": "Колбаса и сосиски", "sentences": ["Пирог Самокат с сыром и шпинатом, 250 г", "Сосиски Самокат, из куриной грудки, 400 г", "Суп-лапша Vifon, Ramen, с соевым соусом и морскими водорослями, быстрого приготовления, 80 г"]}, {"source_sentence": "кола", "sentences": ["Уха по-карельски Самокат, с сёмгой, 270 г", "Кола Самокат, с газом, 1 л", "Томатный соус Mutti, с овощами гриль, 400 г"]}, {"source_sentence": "мука", "sentences": ["Фруктовые кусочки ФрутоНяня, Фрутохвостики, яблоко и земляника, с 12 месяцев, 15 г", "Закуска овощная Balkanika Лютеница икра из печёного перца и баклажана, 360 г", "Лапша Big Bon Wok, курица в соусе терияки, быстрого приготовления, 85 г"]}, {"source_sentence": "сок лайма", "sentences": ["Сливки Домик в деревне, 20%, стерилизованные, 475 мл", "Томаты Flamenco, сливовидные, 450 г", "Сывороточно-молочный напиток Мажитэль, с соком, яблоко, лайм и мята, 950 г"]}, {"source_sentence": "Уксус 9%", "sentences": ["Копчёные перепелиные яйца Самокат, 15 шт.", "Сырный соус Самокат, 90 г", "Сэндвич Mátes, с индейкой монре, 185 г"]}], "model-index": null, "config": {"architectures": ["XLMRobertaModel"], "model_type": "xlm-roberta", "tokenizer_config": {"bos_token": "<s>", "cls_token": "<s>", "eos_token": "</s>", "mask_token": "<mask>", "pad_token": "<pad>", "sep_token": "</s>", "unk_token": "<unk>"}}, "cardData": {"tags": ["sentence-transformers", "sentence-similarity", "feature-extraction", "dense", "generated_from_trainer", "dataset_size:19210", "loss:CoSENTLoss"], "base_model": "deepvk/USER-bge-m3", "widget": [{"source_sentence": "Колбаса и сосиски", "sentences": ["Пирог Самокат с сыром и шпинатом, 250 г", "Сосиски Самокат, из куриной грудки, 400 г", "Суп-лапша Vifon, Ramen, с соевым соусом и морскими водорослями, быстрого приготовления, 80 г"]}, {"source_sentence": "кола", "sentences": ["Уха по-карельски Самокат, с сёмгой, 270 г", "Кола Самокат, с газом, 1 л", "Томатный соус Mutti, с овощами гриль, 400 г"]}, {"source_sentence": "мука", "sentences": ["Фруктовые кусочки ФрутоНяня, Фрутохвостики, яблоко и земляника, с 12 месяцев, 15 г", "Закуска овощная Balkanika Лютеница икра из печёного перца и баклажана, 360 г", "Лапша Big Bon Wok, курица в соусе терияки, быстрого приготовления, 85 г"]}, {"source_sentence": "сок лайма", "sentences": ["Сливки Домик в деревне, 20%, стерилизованные, 475 мл", "Томаты Flamenco, сливовидные, 450 г", "Сывороточно-молочный напиток Мажитэль, с соком, яблоко, лайм и мята, 950 г"]}, {"source_sentence": "Уксус 9%", "sentences": ["Копчёные перепелиные яйца Самокат, 15 шт.", "Сырный соус Самокат, 90 г", "Сэндвич Mátes, с индейкой монре, 185 г"]}], "pipeline_tag": "sentence-similarity", "library_name": "sentence-transformers"}, "siblings": [{"rfilename": ".gitattributes"}, {"rfilename": "1_Pooling/config.json"}, {"rfilename": "README.md"}, {"rfilename": "config.json"}, {"rfilename": "config_sentence_transformers.json"}, {"rfilename": "model.safetensors"}, {"rfilename": "modules.json"}, {"rfilename": "sentence_bert_config.json"}, {"rfilename": "sentencepiece.bpe.model"}, {"rfilename": "special_tokens_map.json"}, {"rfilename": "tokenizer.json"}, {"rfilename": "tokenizer_config.json"}], "spaces": [], "createdAt": "2025-08-21T16:41:52.000Z", "safetensors": {"parameters": {"F32": 359026688}, "total": 359026688}, "usedStorage": 2873346258, "downloadsAllTime": 17, "inferenceProviderMapping": {}, "configJson": {"architectures": ["XLMRobertaModel"], "attention_probs_dropout_prob": 0.1, "bos_token_id": 0, "classifier_dropout": null, "eos_token_id": 2, "hidden_act": "gelu", "hidden_dropout_prob": 0.1, "hidden_size": 1024, "initializer_range": 0.02, "intermediate_size": 4096, "layer_norm_eps": 1e-05, "max_position_embeddings": 8194, "model_type": "xlm-roberta", "num_attention_heads": 16, "num_hidden_layers": 24, "output_past": true, "pad_token_id": 1, "position_embedding_type": "absolute", "torch_dtype": "float32", "transformers_version": "4.55.0", "type_vocab_size": 1, "use_cache": true, "vocab_size": 46166}, "onnxFiles": {}, "safetensorsSizeMb": 1436.2, "approxSizeMb": 1436.1, "fetchedAt": "2026-06-09T06:55:53.000Z"}