{"_id": "68b95db6bdc4ee5d5dc66a35", "id": "mradermacher/sarashina-embedding-v2-1b-GGUF", "private": false, "pipeline_tag": "feature-extraction", "library_name": "transformers", "tags": ["transformers", "gguf", "sentence-similarity", "feature-extraction", "sentence-transformers", "ja", "base_model:sbintuitions/sarashina-embedding-v2-1b", "base_model:quantized:sbintuitions/sarashina-embedding-v2-1b", "endpoints_compatible", "region:us"], "downloads": 88, "likes": 2, "modelId": "mradermacher/sarashina-embedding-v2-1b-GGUF", "author": "mradermacher", "sha": "e9da43c2a830b1fa419e7bb011f537d4b4b66487", "lastModified": "2025-09-04T09:47:52.000Z", "gated": false, "disabled": false, "model-index": null, "config": {}, "cardData": {"base_model": "sbintuitions/sarashina-embedding-v2-1b", "language": ["ja"], "library_name": "transformers", "license_link": "LICENSE", "license_name": "sarahina-non-commercial-license", "mradermacher": {"readme_rev": 1}, "quantized_by": "mradermacher", "tags": ["transformers", "sentence-similarity", "feature-extraction", "sentence-transformers"]}, "transformersInfo": {"auto_model": "AutoModel"}, "gguf": {"total": 1224038144, "architecture": "llama", "context_length": 8192, "bos_token": "<s>", "eos_token": "</s>", "totalFileSize": 2450815072}, "siblings": [{"rfilename": ".gitattributes"}, {"rfilename": "README.md"}, {"rfilename": "sarashina-embedding-v2-1b.IQ4_XS.gguf"}, {"rfilename": "sarashina-embedding-v2-1b.Q2_K.gguf"}, {"rfilename": "sarashina-embedding-v2-1b.Q3_K_L.gguf"}, {"rfilename": "sarashina-embedding-v2-1b.Q3_K_M.gguf"}, {"rfilename": "sarashina-embedding-v2-1b.Q3_K_S.gguf"}, {"rfilename": "sarashina-embedding-v2-1b.Q4_K_M.gguf"}, {"rfilename": "sarashina-embedding-v2-1b.Q4_K_S.gguf"}, {"rfilename": "sarashina-embedding-v2-1b.Q5_K_M.gguf"}, {"rfilename": "sarashina-embedding-v2-1b.Q5_K_S.gguf"}, {"rfilename": "sarashina-embedding-v2-1b.Q6_K.gguf"}, {"rfilename": "sarashina-embedding-v2-1b.Q8_0.gguf"}, {"rfilename": "sarashina-embedding-v2-1b.f16.gguf"}], "spaces": [], "createdAt": "2025-09-04T09:36:54.000Z", "usedStorage": 11575954560, "downloadsAllTime": 1292, "inferenceProviderMapping": {}, "configJson": null, "onnxFiles": {}, "safetensorsSizeMb": 0.0, "approxSizeMb": 0.0, "fetchedAt": "2026-06-08T16:42:43.000Z"}