{"_id": "69c2622468beac1fd989d891", "id": "Jimmy-Ooi/TTM_1239_16_15_0.0001_AdamW", "private": false, "pipeline_tag": "sentence-similarity", "library_name": "sentence-transformers", "tags": ["sentence-transformers", "safetensors", "bert", "sentence-similarity", "feature-extraction", "dense", "generated_from_trainer", "dataset_size:286816", "loss:SoftmaxLoss", "arxiv:1908.10084", "base_model:google-bert/bert-base-cased", "base_model:finetune:google-bert/bert-base-cased", "text-embeddings-inference", "endpoints_compatible", "region:us"], "downloads": 1, "likes": 0, "modelId": "Jimmy-Ooi/TTM_1239_16_15_0.0001_AdamW", "author": "Jimmy-Ooi", "sha": "fa1973992cdcacb6f0a172f5fd90c1de6f8d24bc", "lastModified": "2026-03-24T10:06:52.000Z", "gated": false, "disabled": false, "mask_token": "[MASK]", "widgetData": [{"source_sentence": "CC1=CC[C@@H](C(C)(C)O[C@@H]2O[C@H](CO)[C@@H](O)[C@H](O)[C@H]2O)CC1", "sentences": ["CCc1ccccc1NC(N)=S", "CNC(=S)N/N=C(\\C)c1ccc(O)cc1O", "O=C(O)CSc1nnc(NC(=S)Nc2ccccc2)s1"]}, {"source_sentence": "CCCCCCCC/C(I)=C(/I)CCCCCCCC(=O)OCC(COC(=O)CCCCCCC/C(I)=C(/I)CCCCCCCC)OC(=O)CCCCCCC/C(I)=C(/I)CCCCCCCC", "sentences": ["Cc1nnc(SCc2cc(=O)c(O)co2)n1NCc1ccccc1O", "O=C1/C(=C/c2ccc(O)c(Br)c2)CSc2ccccc21", "O/N=C(\\C=C\\c1ccccn1)c1cc2ccccc2cc1O"]}, {"source_sentence": "C[C@]12CC[C@@H](O)[C@@](C)(C(=O)O)[C@@H]1CC[C@]1(C)[C@@H]2CC[C@@H]2[C@H]3[C@H]([C@](C)(O)CO)CC[C@]3(C(=O)O)CC[C@]21C", "sentences": ["COc1cc([C@H]2Oc3ccc([C@H]4Oc5cc(O)cc(O)c5C(=O)[C@@H]4O)cc3O[C@@H]2CO)ccc1O", "C=C(C)[C@@H]1CC[C@]2(C(=O)O)CC[C@]3(C)[C@H](CC[C@@H]4[C@@]5(C)CC[C@@H](O)[C@@](C)(C=O)[C@@H]5CC[C@]43C)[C@@H]12", "COc1ccc(C(=O)N/N=C/c2cc(OC)c(OC)c(OC)c2)cc1OC"]}, {"source_sentence": "NC(=S)NCc1ccccc1", "sentences": ["COc1cc(C=O)c2c(=O)c3ccccc3oc2c1OC", "O=C(/C=C/c1ccc(O)cc1O)c1ccc(O)cc1O", "C/C(=N\\NC(N)=S)c1cccc(NC(=O)C(F)(F)F)c1"]}, {"source_sentence": "O=C(c1ccc2ccccc2c1)N1CCC(N2CCCCC2)CC1", "sentences": ["N[C@@H](Cc1ccccc1)C(=O)N[C@@H](Cc1ccccc1)C(=O)OCc1cc(=O)c(O)c[nH]1", "CC(=O)Nc1cccc(/C(C)=N/NC(N)=S)c1", "O=C(OCc1cccc(O)c1)c1cc(O)c(O)c(O)c1"]}], "model-index": null, "config": {"architectures": ["BertModel"], "model_type": "bert", "tokenizer_config": {"cls_token": "[CLS]", "mask_token": "[MASK]", "pad_token": "[PAD]", "sep_token": "[SEP]", "unk_token": "[UNK]"}}, "cardData": {"tags": ["sentence-transformers", "sentence-similarity", "feature-extraction", "dense", "generated_from_trainer", "dataset_size:286816", "loss:SoftmaxLoss"], "base_model": "google-bert/bert-base-cased", "widget": [{"source_sentence": "CC1=CC[C@@H](C(C)(C)O[C@@H]2O[C@H](CO)[C@@H](O)[C@H](O)[C@H]2O)CC1", "sentences": ["CCc1ccccc1NC(N)=S", "CNC(=S)N/N=C(\\C)c1ccc(O)cc1O", "O=C(O)CSc1nnc(NC(=S)Nc2ccccc2)s1"]}, {"source_sentence": "CCCCCCCC/C(I)=C(/I)CCCCCCCC(=O)OCC(COC(=O)CCCCCCC/C(I)=C(/I)CCCCCCCC)OC(=O)CCCCCCC/C(I)=C(/I)CCCCCCCC", "sentences": ["Cc1nnc(SCc2cc(=O)c(O)co2)n1NCc1ccccc1O", "O=C1/C(=C/c2ccc(O)c(Br)c2)CSc2ccccc21", "O/N=C(\\C=C\\c1ccccn1)c1cc2ccccc2cc1O"]}, {"source_sentence": "C[C@]12CC[C@@H](O)[C@@](C)(C(=O)O)[C@@H]1CC[C@]1(C)[C@@H]2CC[C@@H]2[C@H]3[C@H]([C@](C)(O)CO)CC[C@]3(C(=O)O)CC[C@]21C", "sentences": ["COc1cc([C@H]2Oc3ccc([C@H]4Oc5cc(O)cc(O)c5C(=O)[C@@H]4O)cc3O[C@@H]2CO)ccc1O", "C=C(C)[C@@H]1CC[C@]2(C(=O)O)CC[C@]3(C)[C@H](CC[C@@H]4[C@@]5(C)CC[C@@H](O)[C@@](C)(C=O)[C@@H]5CC[C@]43C)[C@@H]12", "COc1ccc(C(=O)N/N=C/c2cc(OC)c(OC)c(OC)c2)cc1OC"]}, {"source_sentence": "NC(=S)NCc1ccccc1", "sentences": ["COc1cc(C=O)c2c(=O)c3ccccc3oc2c1OC", "O=C(/C=C/c1ccc(O)cc1O)c1ccc(O)cc1O", "C/C(=N\\NC(N)=S)c1cccc(NC(=O)C(F)(F)F)c1"]}, {"source_sentence": "O=C(c1ccc2ccccc2c1)N1CCC(N2CCCCC2)CC1", "sentences": ["N[C@@H](Cc1ccccc1)C(=O)N[C@@H](Cc1ccccc1)C(=O)OCc1cc(=O)c(O)c[nH]1", "CC(=O)Nc1cccc(/C(C)=N/NC(N)=S)c1", "O=C(OCc1cccc(O)c1)c1cc(O)c(O)c(O)c1"]}], "pipeline_tag": "sentence-similarity", "library_name": "sentence-transformers"}, "siblings": [{"rfilename": ".gitattributes"}, {"rfilename": "1_Pooling/config.json"}, {"rfilename": "README.md"}, {"rfilename": "config.json"}, {"rfilename": "config_sentence_transformers.json"}, {"rfilename": "model.safetensors"}, {"rfilename": "modules.json"}, {"rfilename": "sentence_bert_config.json"}, {"rfilename": "tokenizer.json"}, {"rfilename": "tokenizer_config.json"}], "spaces": [], "createdAt": "2026-03-24T10:06:28.000Z", "safetensors": {"parameters": {"F32": 108310272}, "total": 108310272}, "usedStorage": 433263424, "downloadsAllTime": 56, "inferenceProviderMapping": {}, "configJson": {"add_cross_attention": false, "architectures": ["BertModel"], "attention_probs_dropout_prob": 0.1, "bos_token_id": null, "classifier_dropout": null, "dtype": "float32", "eos_token_id": null, "gradient_checkpointing": false, "hidden_act": "gelu", "hidden_dropout_prob": 0.1, "hidden_size": 768, "initializer_range": 0.02, "intermediate_size": 3072, "is_decoder": false, "layer_norm_eps": 1e-12, "max_position_embeddings": 512, "model_type": "bert", "num_attention_heads": 12, "num_hidden_layers": 12, "pad_token_id": 0, "position_embedding_type": "absolute", "tie_word_embeddings": true, "transformers_version": "5.3.0", "type_vocab_size": 2, "use_cache": true, "vocab_size": 28996}, "onnxFiles": {}, "safetensorsSizeMb": 433.3, "approxSizeMb": 433.2, "fetchedAt": "2026-06-10T07:15:01.000Z"}